{"horoscope":{"2024/03/29":[{"content":"何事にも妥協をしないのが、開運のきっかけになります。言わなければいけないことは、心を鬼にして口にしてください。","item":"デニムジャケット","money":3,"total":3,"job":3,"color":"レッド","day":29,"love":4,"rank":7,"sign":"牡羊座"},{"content":"運気はイマイチなので、小さいミスに注意。立ち居振る舞いに気をつけておくと、仕事や趣味の場で人付き合いがうまくなりそう。","item":"玄米","money":2,"total":2,"job":2,"color":"ブラック","day":"","love":2,"rank":11,"sign":"牡牛座"},{"content":"仕事のやる気がアップしそうな日☆ちょっと言いにくいことがある人には、メールなどでやんわり伝えるのがいいかも。","item":"指輪","money":4,"total":4,"job":5,"color":"ピンク","day":"","love":5,"rank":3,"sign":"双子座"},{"content":"あなたのさりげない気配りが、周りを笑顔にする日。人間関係がスムーズになって、ストレスもなく過ごせるはずです☆","item":"キーケース","money":4,"total":4,"job":4,"color":"グリーン","day":"","love":5,"rank":4,"sign":"蟹座"},{"content":"自分にも他人にも厳しくなってしまいそう。多少のミスなら、笑って流すことが大事です。疲れたらすぐに気分転換をして。","item":"グルメ情報誌","money":1,"total":1,"job":2,"color":"ホワイト","day":"","love":2,"rank":12,"sign":"獅子座"},{"content":"会ってみたい人がいるなら、近い人脈の知り合いを頼ってみましょう。あなたの働きかけで、嬉しい出会いがあるかも。","item":"ちらし寿司","money":3,"total":3,"job":3,"color":"オレンジ","day":"","love":3,"rank":8,"sign":"乙女座"},{"content":"ネットで知り合った人から、いい情報をもらえそう。同じ趣味の仲間がいるコミュニティーは、大事にしておきましょう。","item":"英会話の教材","money":3,"total":4,"job":4,"color":"ブルー","day":"","love":4,"rank":5,"sign":"天秤座"},{"content":"決断したいことがあるのなら、思い切って一番難しい道を選んでみましょう。意外にあっさりクリアできて、満足度も十分。","item":"マシュマロ","money":2,"total":3,"job":3,"color":"ゴールド","day":"","love":3,"rank":9,"sign":"蠍座"},{"content":"誰かのミスをカバーしてあげると、あなたの評価が上がりそう。気になる人も、一目置いてくれるかも！恩着せがましくしないでね☆","item":"しょうゆラーメン","money":4,"total":5,"job":5,"color":"イエロー","day":"","love":5,"rank":2,"sign":"射手座"},{"content":"人の視線を気にしていると、あなたのやりたいことができないかも。何をいわれてもいいと開き直れば、運気が向いてきます。","item":"中華丼","money":2,"total":2,"job":2,"color":"パープル","day":"","love":3,"rank":10,"sign":"山羊座"},{"content":"今日は恋も仕事も絶好調！お気に入りの場所に、あなたから恋人を誘って出かけてみて。お互いの新たな魅力を発見できます。","item":"お好み焼き","money":5,"total":5,"job":5,"color":"シルバー","day":"","love":5,"rank":1,"sign":"水瓶座"},{"content":"カバンやパソコンの中身をきれいにしておくと、気分がすっきりします。気になる人がいる場合は、趣味の話をしてみて。","item":"ノンシュガーの飲み物","money":3,"total":3,"job":4,"color":"グレー","day":"","love":4,"rank":6,"sign":"魚座"}]}}