{"horoscope":{"2023/11/22":[{"content":"どんなことにも新鮮な魅力を見つけることができて、感動しそうな日です。会いたい人がいるなら、ぜひ連絡を取ってみて☆","item":"座布団","money":5,"total":4,"job":4,"color":"レッド","day":22,"love":5,"rank":3,"sign":"牡羊座"},{"content":"同じ考え方、価値観にとらわれていると、うまくいかない暗示。最近知り合った人の話を聞くと、いいアイディアが閃きそうです。","item":"旅行のガイドブック","money":2,"total":2,"job":3,"color":"イエロー","day":"","love":2,"rank":10,"sign":"牡牛座"},{"content":"今日は会話で周りを楽しませ、自分のペースに乗せることができます。気になるあの人にも積極的に話しかけてみましょう。","item":"革の財布","money":3,"total":3,"job":4,"color":"グリーン","day":"","love":3,"rank":7,"sign":"双子座"},{"content":"苦手な作業に、たくさん時間を取られてしまうかも。身近に頼れる人がいるなら、甘えても良さそう。意地を張らないようにして。","item":"歯ブラシ","money":2,"total":1,"job":1,"color":"パープル","day":"","love":2,"rank":12,"sign":"蟹座"},{"content":"忙しい環境から離れる時間が、今日のあなたには必要です。ゆっくり半身浴もいいでしょう。自然とパワーが湧いてくるかも。","item":"マグカップ","money":3,"total":3,"job":2,"color":"ゴールド","day":"","love":3,"rank":9,"sign":"獅子座"},{"content":"疲れが溜まってきたと思ったら、身の周りの整理で気分転換。思い切って部屋の模様替えをすると、明るい気持ちになれそうです。","item":"双眼鏡","money":4,"total":4,"job":3,"color":"ピンク","day":"","love":4,"rank":5,"sign":"乙女座"},{"content":"自然に触れることで運気アップ。昼休みは公園で過ごすと、ストレス発散に。スポーツを始めると、仲間が見つかるかも♪","item":"柿","money":5,"total":5,"job":4,"color":"グレー","day":"","love":5,"rank":2,"sign":"天秤座"},{"content":"何事も予定通りに進んで、プライベートの時間が充実しそう。たまには同僚を誘って、会社以外での親睦を深めてみては。","item":"マウスパッド","money":3,"total":3,"job":3,"color":"ホワイト","day":"","love":3,"rank":8,"sign":"蠍座"},{"content":"頭の回転がとても速くなる日です。さまざまな場面で、そのときに最適な振る舞いができて、あなたの評価が上がりそう♪","item":"熱帯魚","money":4,"total":4,"job":5,"color":"オレンジ","day":"","love":4,"rank":4,"sign":"射手座"},{"content":"たくさんの情報が飛び込んでくる日。仕事や勉強、プライベートなど、あらゆる面で変化があり、サプライズもありそう！","item":"イヤリング","money":5,"total":5,"job":5,"color":"シルバー","day":"","love":5,"rank":1,"sign":"山羊座"},{"content":"努力を重ねた分だけ、あなたの実力になりそう。遊びたい衝動にかられても、今はぐっと我慢。先を見据えて動くと◎。","item":"スニーカー","money":4,"total":3,"job":3,"color":"ブラック","day":"","love":4,"rank":6,"sign":"水瓶座"},{"content":"悩み事が大きくなりそう。もし、誰かに相談したいことがあるなら、早めにしておきましょう。自分を責めないようにして。","item":"楽譜","money":2,"total":2,"job":2,"color":"ブルー","day":"","love":2,"rank":11,"sign":"魚座"}]}}