{"horoscope":{"2024/07/14":[{"content":"家族や友達と、ケンカをしてしまうかも。あなたの発言にもうっかりミスがあるので、できるだけ今日は冷静に行動をして。","item":"マスタード","money":2,"total":2,"job":2,"color":"ブラック","day":14,"love":2,"rank":11,"sign":"牡羊座"},{"content":"受けた恩は必ず返すこと。今日はいろんな人にお世話になりそうです。友達からサポートを受けたら、今日のうちに何かお礼を。","item":"風鈴","money":3,"total":3,"job":4,"color":"グレー","day":"","love":3,"rank":7,"sign":"牡牛座"},{"content":"意中の人からあなたに接近の予感！心の準備をしておいて。カップルは相手の愚痴を聞いてあげましょう。甘えてくれそう。","item":"恋愛小説","money":5,"total":5,"job":5,"color":"ピンク","day":"","love":5,"rank":1,"sign":"双子座"},{"content":"ダラダラしてしまいそうな日です。仕事や勉強に支障をきたしそう。何をやるにしても、時間の区切りをしっかりと付けて。","item":"みそラーメン","money":2,"total":1,"job":1,"color":"パープル","day":"","love":2,"rank":12,"sign":"蟹座"},{"content":"あなたのひらめきが、いろんな人の役に立ちそうです。ミーティングなどでは、ぜひ思ったことを口にしてみてください☆","item":"万年筆","money":5,"total":5,"job":4,"color":"シルバー","day":"","love":5,"rank":2,"sign":"獅子座"},{"content":"少し前から悩んでいた問題が、取り越し苦労だったとわかりそうです。今日は受け身でいるより、積極的に発信しましょう！","item":"チョーカー","money":5,"total":4,"job":4,"color":"イエロー","day":"","love":5,"rank":3,"sign":"乙女座"},{"content":"これはこうでないといけない、という考えはダメ。何事も自由なアイディアを活かしましょう。ミスは次に活かせば問題なし。","item":"コルクボード","money":3,"total":3,"job":2,"color":"ゴールド","day":"","love":3,"rank":9,"sign":"天秤座"},{"content":"あなたを手助けしてくれる人が現れそう。悪い結果を恐れずに、大胆に行動してみましょう。恋愛に新たな局面があるかも。","item":"水餃子","money":3,"total":3,"job":3,"color":"オレンジ","day":"","love":3,"rank":8,"sign":"蠍座"},{"content":"好きな人の言葉が、あなたを勇気付けてくれそう。お世話になっていると思ったら、ぜひお礼を。夜は家族との時間も大切にして。","item":"しょうゆ","money":2,"total":2,"job":3,"color":"ブルー","day":"","love":2,"rank":10,"sign":"射手座"},{"content":"勉強に対するモチベーションが、大きく変わる一日です。尊敬する人と一緒にいると、あなたのスキルまでアップする暗示。","item":"写真立て","money":4,"total":3,"job":3,"color":"グリーン","day":"","love":4,"rank":6,"sign":"山羊座"},{"content":"新しい恋の期待が持てる一日。今日は言葉遣いや服装などを少し違った雰囲気にしてみて。ギャップにときめく人が現れそう。","item":"スウェット","money":4,"total":4,"job":3,"color":"ホワイト","day":"","love":4,"rank":5,"sign":"水瓶座"},{"content":"メモの習慣を付けたい日。気づきを書けば、それは大きなモノを生み出します。本を読んだり、映画を見たりという経験も大事☆","item":"ピーナッツ","money":4,"total":4,"job":5,"color":"レッド","day":"","love":4,"rank":4,"sign":"魚座"}]}}