{"horoscope":{"2025/02/21":[{"content":"仕事のルーティンを再確認すると、新しい発見がありそう。プライベートな時間は、うまく息抜きができるように過ごして。","item":"チョコレートクッキー","money":3,"total":3,"job":4,"color":"ホワイト","day":21,"love":3,"rank":7,"sign":"牡羊座"},{"content":"今日は仕事とプライベートを完全に割りきって。遊びの約束を断っても仕事に集中できれば、努力の成果は大きいでしょう。","item":"コンソメスープ","money":4,"total":3,"job":3,"color":"パープル","day":"","love":4,"rank":6,"sign":"牡牛座"},{"content":"せかせかと動き回るより、のんびり構えて正解。気ままに散歩をしたり買い物に出かけたりすることも、時には必要かも。","item":"カットフルーツ","money":4,"total":4,"job":3,"color":"イエロー","day":"","love":4,"rank":5,"sign":"双子座"},{"content":"何かと人から相談されそう。期待に応えてあげた分だけ運気は上昇。面倒くさがらずに、誠実に話を聞いてあげましょう。","item":"サーロインステーキ","money":2,"total":2,"job":2,"color":"ブルー","day":"","love":2,"rank":11,"sign":"蟹座"},{"content":"思い出の品物や写真を整理すると、未来に向けて前向きな気持ちになれそうです。昔の友達に連絡をとるのもオススメ。","item":"親子丼","money":2,"total":2,"job":3,"color":"ピンク","day":"","love":2,"rank":10,"sign":"獅子座"},{"content":"あまり親しくない人が多いイベントでも、楽しむ意識をもって臨んで。予想以上にステキな思い出を作ることができそうです。","item":"フルーツジュース","money":5,"total":5,"job":5,"color":"オレンジ","day":"","love":5,"rank":1,"sign":"乙女座"},{"content":"落ち込んでいても、人からの温かい言葉で勇気をもらえそう。どんな人からのアドバイスにも、素直に耳を傾けることが大切♪","item":"ガラスの置物","money":4,"total":4,"job":5,"color":"シルバー","day":"","love":4,"rank":4,"sign":"天秤座"},{"content":"常識やマナーの意識を見直すと、周りからの印象度が変わりそう。ちょっとした工夫で、運気もガラリと良くなります☆","item":"スリッパ","money":5,"total":4,"job":4,"color":"レッド","day":"","love":5,"rank":3,"sign":"蠍座"},{"content":"お金を自分に投資すると、良い結果が得られそうです。服を買ったり美容院に行ったりしてイメージチェンジを狙うのも吉☆","item":"シーザーサラダ","money":5,"total":5,"job":4,"color":"ブラック","day":"","love":5,"rank":2,"sign":"射手座"},{"content":"優しい気持ちで過ごせる日。奉仕の心で人と接すると運気アップ。ボランティア活動などにも、関心が生まれそうです。","item":"スピーカー","money":3,"total":3,"job":3,"color":"グレー","day":"","love":3,"rank":8,"sign":"山羊座"},{"content":"困った時には、いつもは意見を求めない友達に、話を聞いてみて。面白い意見が聞けて、モチベーションも回復するでしょう。","item":"靴下","money":2,"total":1,"job":1,"color":"ゴールド","day":"","love":2,"rank":12,"sign":"水瓶座"},{"content":"穏やかで充実した日になりそう。難しい本を読んだり美術館に行ったりして感性を刺激すると、ひらめき力がアップします。","item":"音楽雑誌","money":3,"total":3,"job":2,"color":"グリーン","day":"","love":3,"rank":9,"sign":"魚座"}]}}