{"horoscope":{"2023/11/11":[{"content":"運気は好調☆お気に入りにできるお店が見つかりそう。ガイドブックを頼るよりも、あなたの感覚に従って歩いてみて。","item":"キーケース","money":4,"total":4,"job":4,"color":"グリーン","day":11,"love":5,"rank":4,"sign":"牡羊座"},{"content":"考え方を変えるだけで、チャンスを広げることができそう。準備も早めにスタートさせて。余裕を持った行動がポイントに♪","item":"ウクレレ","money":4,"total":4,"job":5,"color":"イエロー","day":"","love":5,"rank":3,"sign":"牡牛座"},{"content":"アンラッキーな出来事は、今の自分を変えるきっかけだと思って正解。困ったことが起きたら、家族に相談をしてみて。","item":"ホットミルク","money":2,"total":2,"job":2,"color":"ブラック","day":"","love":3,"rank":10,"sign":"双子座"},{"content":"秋らしいファッションで自己主張を。前から気になっていた人が、あなたに声をかけてくれるかも。ニコニコ笑顔で対応して。","item":"和風サラダ","money":3,"total":3,"job":4,"color":"パープル","day":"","love":4,"rank":6,"sign":"蟹座"},{"content":"アイディア力に恵まれる一日です。突然の課題も、あなたの創意工夫でクリア。恋人から嬉しいプレゼントの暗示も！？","item":"シーチキン","money":5,"total":5,"job":5,"color":"シルバー","day":"","love":5,"rank":1,"sign":"獅子座"},{"content":"予定がコロコロ変わりそう。早めに面倒な用事を片付ける日にすれば、運気は好転します。夜は手作りの料理を楽しんで。","item":"圧力鍋","money":3,"total":3,"job":3,"color":"ピンク","day":"","love":4,"rank":7,"sign":"乙女座"},{"content":"切ない恋の相談は、同性の年上の人にすると吉。素直な気持ちで聞くことができれば、チャンスが見えてくるでしょう。","item":"ドライバー","money":1,"total":1,"job":2,"color":"ブルー","day":"","love":2,"rank":12,"sign":"天秤座"},{"content":"好きな人と次のステップに進むには、見つめているだけではダメ。周りに協力してもらい、積極的にチャンスを作るべし☆","item":"日記帳","money":4,"total":5,"job":5,"color":"ゴールド","day":"","love":5,"rank":2,"sign":"蠍座"},{"content":"いつもお世話になっている人に、恩返しできる日です。高価な品物を買うよりも、あなたの気持ちを正直に伝えましょう。","item":"ミックスジュース","money":3,"total":3,"job":3,"color":"レッド","day":"","love":3,"rank":8,"sign":"射手座"},{"content":"人のミスを自分のせいにされて、イライラしてしまうかも。周囲の空気もピリピリしているので、今日はリラックスを心がけて。","item":"サプリメント","money":2,"total":2,"job":2,"color":"ホワイト","day":"","love":2,"rank":11,"sign":"山羊座"},{"content":"身近な人の嬉しいニュースが聞けそうです。お祝いのパーティーは派手に。肌寒さを感じやすいので、厚手のアウターを準備して。","item":"コンタクトレンズ","money":2,"total":3,"job":3,"color":"オレンジ","day":"","love":3,"rank":9,"sign":"水瓶座"},{"content":"自分の考えに固執していると、せっかくの運気アップの機会を逃しそう。他人の意見を受け入れると評価も上がります。","item":"ハンカチ","money":3,"total":4,"job":4,"color":"グレー","day":"","love":4,"rank":5,"sign":"魚座"}]}}