{"horoscope":{"2023/09/05":[{"content":"好きな人の前で、見栄っ張りになって損をしそうな予感。今日はいつも通りのあなたで大丈夫です。お金の管理にも注意を。","item":"小銭入れ","money":2,"total":2,"job":3,"color":"ブラック","day":5,"love":2,"rank":10,"sign":"牡羊座"},{"content":"新しい恋に、焦りは禁物です。進展を急ぐより、相手の気持ちを読み取ることが大事。さりげない気配りで印象アップ☆","item":"チーズケーキ","money":3,"total":3,"job":2,"color":"パープル","day":"","love":3,"rank":9,"sign":"牡牛座"},{"content":"今日はあなたの強気さや積極性が幸運を引き寄せそう！チームのリーダー役を買って出るのもオススメです。自信を持って♪","item":"カチューシャ","money":5,"total":5,"job":5,"color":"ホワイト","day":"","love":5,"rank":1,"sign":"双子座"},{"content":"願い事は、そっと好きな人に伝えて。相手が気を利かせて、叶えてくれるかも。夜は旧友から、楽しいお誘いの暗示も。","item":"赤いボールペン","money":5,"total":4,"job":4,"color":"ブルー","day":"","love":5,"rank":3,"sign":"蟹座"},{"content":"クリエイティブなセンスが発揮され、新しい発見のある一日。仕事に役立つアイディアがあれば、メモをしておきましょう。","item":"ホットドッグ","money":3,"total":3,"job":4,"color":"レッド","day":"","love":3,"rank":7,"sign":"獅子座"},{"content":"大好きな人に会える予定ができて、ウキウキする一日に。相手に好かれるための、あなたらしい駆け引きを考えてみて。","item":"折りたたみの傘","money":4,"total":4,"job":3,"color":"ゴールド","day":"","love":4,"rank":5,"sign":"乙女座"},{"content":"考えすぎで、ストレスが溜まるかも。今日は体を動かして気分転換しましょう。思い切り汗をかくほど没頭してリフレッシュ！","item":"掃除器","money":2,"total":2,"job":2,"color":"イエロー","day":"","love":2,"rank":11,"sign":"天秤座"},{"content":"他人から迷惑をかけられても、自分がかけるよりはマシだと思って正解。クールに頭を動かせば、問題解決はすぐです♪","item":"生クリーム","money":4,"total":4,"job":5,"color":"シルバー","day":"","love":4,"rank":4,"sign":"蠍座"},{"content":"口が災いを呼ぶ一日。尊敬する人や、目上の人への言葉の選び方は特に慎重に。意見がある時は、要点をまとめてから。","item":"のどあめ","money":2,"total":1,"job":1,"color":"グリーン","day":"","love":2,"rank":12,"sign":"射手座"},{"content":"職場の後輩など、年下の人との関係を大切にすると吉。何気ない会話の中で、新しい発見がありそう☆自宅に招くのも◎。","item":"リモコン","money":5,"total":5,"job":4,"color":"グレー","day":"","love":5,"rank":2,"sign":"山羊座"},{"content":"長引いていたケンカは、今日の話し合いで仲直りできそう。意地を張らなければ、相手もすんなり受け入れてくれるでしょう。","item":"乳液","money":3,"total":3,"job":3,"color":"オレンジ","day":"","love":3,"rank":8,"sign":"水瓶座"},{"content":"苦手な作業は後回しにして、今日はのんびりと過ごしましょう。金運は悪くないので、気分転換のショッピングもオススメ。","item":"梅干し","money":4,"total":3,"job":3,"color":"ピンク","day":"","love":4,"rank":6,"sign":"魚座"}]}}