{"horoscope":{"2023/10/18":[{"content":"物事の真実が見えてくる日。人間関係は、あなたのことを大切にしてくれる相手かどうかを、見極めのポイントにして正解。","item":"動物の写真","money":3,"total":4,"job":4,"color":"レッド","day":18,"love":4,"rank":5,"sign":"牡羊座"},{"content":"自宅で引きこもるのはNG。今日はイメージチェンジに良いタイミングです。髪型は前髪をアレンジするだけでも良さそう。","item":"ほうじ茶","money":2,"total":2,"job":2,"color":"グリーン","day":"","love":2,"rank":11,"sign":"牡牛座"},{"content":"これまでの悩みが解決する、嬉しい一日です☆あなたを応援してくれる人が見つかるので、ぜひ頼らせてもらいましょう。","item":"鉛筆削り","money":4,"total":4,"job":4,"color":"グレー","day":"","love":5,"rank":4,"sign":"双子座"},{"content":"イメチェンが成功する日。自分に本当に似合うファッションやヘアスタイルは、プロの人の意見を聞いてみると良さそう。","item":"スーツ","money":3,"total":3,"job":3,"color":"ゴールド","day":"","love":4,"rank":7,"sign":"蟹座"},{"content":"知らないことはそのままにしないで。詳しく調べてみると、より深い世界を知ることができて、好奇心が満たされそうです。","item":"ヘアクリップ","money":2,"total":2,"job":2,"color":"ホワイト","day":"","love":3,"rank":10,"sign":"獅子座"},{"content":"向上心が強くなって、周囲も驚くような行動に出そう。あなたの思い切りの良さに影響される人もいて、ツキのある一日に！","item":"ロールケーキ","money":5,"total":5,"job":5,"color":"ピンク","day":"","love":5,"rank":1,"sign":"乙女座"},{"content":"何事も、無謀な挑戦はダメ。下調べしたり、情報を集めたりすることも大切です。年上の人にアドバイスをもらうのもオススメ。","item":"虫眼鏡","money":2,"total":3,"job":3,"color":"ブルー","day":"","love":3,"rank":9,"sign":"天秤座"},{"content":"成長している自分を感じるためには、日記がオススメ。人に話せないような考えや、小さな出来事などを箇条書きにしてみて。","item":"酵素ドリンク","money":3,"total":3,"job":3,"color":"ブラック","day":"","love":3,"rank":8,"sign":"蠍座"},{"content":"先輩からの話は、ちゃんとメモしておいて。パソコンや携帯電話のメモ機能が気軽で便利です。向上心が運気アップのカギに♪","item":"メロンパン","money":4,"total":5,"job":5,"color":"パープル","day":"","love":5,"rank":2,"sign":"射手座"},{"content":"感性が豊かになる日。本当に良いものとの出会いがありそうです。これまでずっと探していたものに会えたら、ぜひ近づいて♪","item":"ノートパソコン","money":4,"total":4,"job":5,"color":"オレンジ","day":"","love":5,"rank":3,"sign":"山羊座"},{"content":"あなたの思い込みを人に指摘されるかもしれません。誰にでも思い違いはあるもの。笑顔でさらりと対応すれば問題なし。","item":"シフォンケーキ","money":3,"total":3,"job":4,"color":"イエロー","day":"","love":4,"rank":6,"sign":"水瓶座"},{"content":"過去の失敗を思い出して、ついモチベーションが下がってしまうかも。不安な気持ちになったら、カフェタイムで気分転換を♪","item":"カスタードクリーム","money":1,"total":1,"job":2,"color":"シルバー","day":"","love":2,"rank":12,"sign":"魚座"}]}}