{"horoscope":{"2024/05/24":[{"content":"自分だけで頑張ろうとせずに、リーダー役の人に合わせるのも大事。責任感を持つのもいいですが、人を頼ってみてください。","item":"ネクタイ","money":3,"total":2,"job":2,"color":"ブラック","day":24,"love":2,"rank":10,"sign":"牡羊座"},{"content":"イベントの計画があるなら、幹事に立候補を。たくさんのアイディアを出して、準備段階からみんなを楽しめることができそう。","item":"古い手紙","money":3,"total":3,"job":3,"color":"ゴールド","day":"","love":3,"rank":8,"sign":"牡牛座"},{"content":"忙しい時期は終わって、リラックスできる一日。気の合う友達と食事に出かけると、のんびり疲れを癒してもらえそう。","item":"コーンポタージュ","money":4,"total":3,"job":4,"color":"パープル","day":"","love":3,"rank":6,"sign":"双子座"},{"content":"今日は人の意見に乗っかった方がいいでしょう。上司や先輩を立てる行動がツキを呼びそうです。自慢話はしないように。","item":"卓上コンロ","money":2,"total":2,"job":2,"color":"イエロー","day":"","love":2,"rank":11,"sign":"蟹座"},{"content":"今日はお得な買い物ができそうです。新しいスマートフォンやカバンを買うのも◎。ネットの口コミを参考にして正解！","item":"週刊誌","money":5,"total":5,"job":5,"color":"ホワイト","day":"","love":5,"rank":1,"sign":"獅子座"},{"content":"いろんな意見を耳にして疲れそう。何事にも、ハッキリした態度をとることが成功のカギかも。気分転換はマメにして。","item":"スポーツドリンク","money":2,"total":1,"job":2,"color":"グリーン","day":"","love":1,"rank":12,"sign":"乙女座"},{"content":"暗い気持ちには今日で区切りがつきそうです。楽しい音楽で盛り上がれば、ストレスも発散できそう。家族との会話も大事に。","item":"パイプ椅子","money":4,"total":4,"job":4,"color":"オレンジ","day":"","love":3,"rank":5,"sign":"天秤座"},{"content":"運気は好調。マニアックな人の趣味に付き合うと、新しい世界を見られて刺激を受けそう。オンラインサロンへの参加も◎。","item":"ミニスカート","money":4,"total":3,"job":3,"color":"ブルー","day":"","love":3,"rank":7,"sign":"蠍座"},{"content":"仕事の選択肢の幅が広がるでしょう。狭い枠組みから飛び出して、可能性を追求できそう。昇給の可能性もあります♪","item":"ガスコンロ","money":5,"total":4,"job":4,"color":"ピンク","day":"","love":4,"rank":4,"sign":"射手座"},{"content":"夢中になれる趣味が見つかる予感。友達が楽しそうにやっていることには、ぜひ興味を持って。素敵な出会いの予感も☆","item":"焼き鳥","money":5,"total":4,"job":5,"color":"レッド","day":"","love":4,"rank":3,"sign":"山羊座"},{"content":"何気ない会話の中に、今まで気づかなかった真実が隠れているかもしれません。人の話を注意深く聞くようにしてください☆","item":"計量カップ","money":5,"total":5,"job":5,"color":"シルバー","day":"","love":4,"rank":2,"sign":"水瓶座"},{"content":"最近知り合ったばかりの人とは、まず積極的に会話してみるとよさそうです。新しい価値観を取り入れて、いい展開に。","item":"ダイエットフード","money":3,"total":3,"job":3,"color":"グレー","day":"","love":2,"rank":9,"sign":"魚座"}]}}