{"Items":[{"Item":{"affiliateRate":"3.0","affiliateUrl":"","asurakuArea":"","asurakuClosingTime":"","asurakuFlag":0,"availability":1,"carrier":0,"catchcopy":"【楽天ブックスならいつでも送料無料】","creditCardFlag":1,"endTime":"","genreId":"112414","imageFlag":1,"itemCaption":"マガジンハウス発売日：2023年06月07日 予約締切日：2023年05月25日 20481 JAN：4910204820631 雑誌 女性誌 女性ファッション 女性誌 情報誌","itemCode":"book:20978157","itemName":"an・an 2023年 6/14号 [雑誌]","itemPrice":"699","itemUrl":"https://item.rakuten.co.jp/book/17523935/","mediumImageUrls":[{"imageUrl":"https://thumbnail.image.rakuten.co.jp/@0_mall/book/cabinet/0631/4910204820631_1_2.jpg?_ex=128x128"}],"pointRate":1,"pointRateEndTime":"","pointRateStartTime":"","postageFlag":0,"rank":1,"reviewAverage":"0.0","reviewCount":0,"shipOverseasArea":"","shipOverseasFlag":0,"shopAffiliateUrl":"","shopCode":"book","shopName":"楽天ブックス","shopOfTheYearFlag":0,"shopUrl":"https://www.rakuten.co.jp/book/","smallImageUrls":[{"imageUrl":"https://thumbnail.image.rakuten.co.jp/@0_mall/book/cabinet/0631/4910204820631_1_2.jpg?_ex=64x64"}],"startTime":"","taxFlag":0}},{"Item":{"affiliateRate":"3.0","affiliateUrl":"","asurakuArea":"","asurakuClosingTime":"","asurakuFlag":0,"availability":0,"carrier":0,"catchcopy":"【楽天ブックスならいつでも送料無料】","creditCardFlag":1,"endTime":"","genreId":"101254","imageFlag":1,"itemCaption":"株式会社シンコーミュージック発行年月：2023年05月31日 予約締切日：2023年05月11日 サイズ：単行本 ISBN：9784401359707 本 エンタメ・ゲーム アニメーション 楽譜 バンドスコア その他","itemCode":"book:20964857","itemName":"バンド・スコア　TVアニメ「ぼっち・ざ・ろっく！」","itemPrice":"3850","itemUrl":"https://item.rakuten.co.jp/book/17510957/","mediumImageUrls":[{"imageUrl":"https://thumbnail.image.rakuten.co.jp/@0_mall/book/cabinet/9707/9784401359707.jpg?_ex=128x128"}],"pointRate":1,"pointRateEndTime":"","pointRateStartTime":"","postageFlag":0,"rank":2,"reviewAverage":"0.0","reviewCount":0,"shipOverseasArea":"","shipOverseasFlag":0,"shopAffiliateUrl":"","shopCode":"book","shopName":"楽天ブックス","shopOfTheYearFlag":0,"shopUrl":"https://www.rakuten.co.jp/book/","smallImageUrls":[{"imageUrl":"https://thumbnail.image.rakuten.co.jp/@0_mall/book/cabinet/9707/9784401359707.jpg?_ex=64x64"}],"startTime":"","taxFlag":0}},{"Item":{"affiliateRate":"3.0","affiliateUrl":"","asurakuArea":"群馬県/埼玉県/千葉県/東京都/神奈川県/新潟県/山梨県/長野県/岐阜県/静岡県/愛知県/三重県/滋賀県/宮城県/福島県/茨城県/栃木県","asurakuClosingTime":"12:00","asurakuFlag":1,"availability":1,"carrier":0,"catchcopy":"【楽天ブックスならいつでも送料無料】","creditCardFlag":1,"endTime":"","genreId":"216751","imageFlag":1,"itemCaption":"MEGUMI 長尾 沙也加 ダイヤモンド社キレイハコレデツクレマス メグミ ナガオ　サヤカ 発行年月：2023年04月20日 予約締切日：2023年02月16日 ページ数：192p サイズ：単行本 ISBN：9784478117293 MEGUMI 女優、タレント。1981年9月25日生まれ、岡山県出身。2001年芸能界デビュー。08年結婚、翌年第1子を出産。雑誌やテレビ番組の他、多くのドラマ・映画に出演する。20年2月、映画「台風家族」「ひとよ」で「第62回ブルーリボン賞」助演女優賞を受賞。現在は代表取締役社長として、個人事務所や金沢のカフェ「たもん」の経営も行っている。美容好きが高じてデビュー時より試した美容法は1000以上。女性がより自信をもって輝くための美容情報の発信にも力を入れている 長尾沙也加（ナガオサヤカ） 医師。THE　ROPPONGI　CLINIC六本木院・恵比寿院代表。抗加齢学会専門医、日本医師会認定産業医。愛知医科大学卒業。東京医科歯科大学医学部附属病院の関連病院である、国家公務員共済組合連合会東京共済病院、および東京医科歯科大学医学部附属病院にて、皮膚科、麻酔科、内科にて美容皮膚科医として勤務。その後、多数の美容皮膚科で経験を重ね、2020年8月THE　ROPPONGI　CLINICを開業、現職（本データはこの書籍が刊行された当時に掲載されていたものです） 1　運命を変えるスキンケア　face（「シートマスク」最強説　潤いと透明感はこの1枚で手に入る／続けるなら「ルルルン」一択！　ほか）／2　自分史上最高メイク　make　up（ドラマや映画は「セルフメイク」で出ています／コツをつかめば「コスメカウンター」は怖くない　ほか）／3　記憶に残す女のカラダ　body（キメの細かい女の肌は「スクラブ」でつくられる／ボディの保湿は絶対「オイル」！　ほか）／4　心を奪う美人のサラ髪　hair（35歳を過ぎたら「髪」がドラマティックな女をつくる／まずは汚れを取らないとはじまらない　ほか）／5　心とカラダをととのえる　mental（自律神経をととのえる「バスタイム」／めんどうなお風呂のテンションを上げるもの　ほか） 「プチプラコスメ」から「美容医療」まで美容オタクMEGUMIが試して選んだ忙しくてもキレイになれる86の美容法！ 本 美容・暮らし・健康・料理 ファッション・美容 その他","itemCode":"book:20896409","itemName":"キレイはこれでつくれます [ MEGUMI ]","itemPrice":"1650","itemUrl":"https://item.rakuten.co.jp/book/17433583/","mediumImageUrls":[{"imageUrl":"https://thumbnail.image.rakuten.co.jp/@0_mall/book/cabinet/7293/9784478117293_1_2.jpg?_ex=128x128"}],"pointRate":1,"pointRateEndTime":"","pointRateStartTime":"","postageFlag":0,"rank":3,"reviewAverage":"4.29","reviewCount":21,"shipOverseasArea":"","shipOverseasFlag":0,"shopAffiliateUrl":"","shopCode":"book","shopName":"楽天ブックス","shopOfTheYearFlag":0,"shopUrl":"https://www.rakuten.co.jp/book/","smallImageUrls":[{"imageUrl":"https://thumbnail.image.rakuten.co.jp/@0_mall/book/cabinet/7293/9784478117293_1_2.jpg?_ex=64x64"}],"startTime":"","taxFlag":0}},{"Item":{"affiliateRate":"3.0","affiliateUrl":"","asurakuArea":"","asurakuClosingTime":"","asurakuFlag":0,"availability":1,"carrier":0,"catchcopy":"【楽天ブックスならいつでも送料無料】","creditCardFlag":1,"endTime":"","genreId":"200478","imageFlag":1,"itemCaption":"日之出出版 マガジンハウスシネマスクエア ヴォリュームヒャクヨンジュウイチ ヒノデシュッパン 発行年月：2023年06月01日 予約締切日：2023年05月19日 ページ数：116p サイズ：ムックその他 ISBN：9784838793990 本 エンタメ・ゲーム 映画 その他","itemCode":"book:20971748","itemName":"シネマスクエア vol.141 [ 日之出出版 ]","itemPrice":"1100","itemUrl":"https://item.rakuten.co.jp/book/17518570/","mediumImageUrls":[{"imageUrl":"https://thumbnail.image.rakuten.co.jp/@0_mall/book/cabinet/3990/9784838793990.gif?_ex=128x128"}],"pointRate":1,"pointRateEndTime":"","pointRateStartTime":"","postageFlag":0,"rank":4,"reviewAverage":"0.0","reviewCount":0,"shipOverseasArea":"","shipOverseasFlag":0,"shopAffiliateUrl":"","shopCode":"book","shopName":"楽天ブックス","shopOfTheYearFlag":0,"shopUrl":"https://www.rakuten.co.jp/book/","smallImageUrls":[{"imageUrl":"https://thumbnail.image.rakuten.co.jp/@0_mall/book/cabinet/3990/9784838793990.gif?_ex=64x64"}],"startTime":"","taxFlag":0}},{"Item":{"affiliateRate":"3.0","affiliateUrl":"","asurakuArea":"","asurakuClosingTime":"","asurakuFlag":0,"availability":1,"carrier":0,"catchcopy":"【楽天ブックスならいつでも送料無料】","creditCardFlag":1,"endTime":"","genreId":"203063","imageFlag":1,"itemCaption":"扶桑社発行年月：2023年07月06日 予約締切日：2023年05月25日 ISBN：9784594095536 本 セット本 その他","itemCode":"book:20977030","itemName":"【楽天ブックス＆Amazon限定】蒼い炎 愛蔵版BOXセット","itemPrice":"9900","itemUrl":"https://item.rakuten.co.jp/book/17524358/","mediumImageUrls":[{"imageUrl":"https://thumbnail.image.rakuten.co.jp/@0_mall/book/cabinet/5536/9784594095536.gif?_ex=128x128"},{"imageUrl":"https://thumbnail.image.rakuten.co.jp/@0_mall/book/cabinet/5536/9784594095536_2.jpg?_ex=128x128"},{"imageUrl":"https://thumbnail.image.rakuten.co.jp/@0_mall/book/cabinet/5536/9784594095536_3.jpg?_ex=128x128"}],"pointRate":1,"pointRateEndTime":"","pointRateStartTime":"","postageFlag":0,"rank":5,"reviewAverage":"0.0","reviewCount":0,"shipOverseasArea":"","shipOverseasFlag":0,"shopAffiliateUrl":"","shopCode":"book","shopName":"楽天ブックス","shopOfTheYearFlag":0,"shopUrl":"https://www.rakuten.co.jp/book/","smallImageUrls":[{"imageUrl":"https://thumbnail.image.rakuten.co.jp/@0_mall/book/cabinet/5536/9784594095536.gif?_ex=64x64"},{"imageUrl":"https://thumbnail.image.rakuten.co.jp/@0_mall/book/cabinet/5536/9784594095536_2.jpg?_ex=64x64"},{"imageUrl":"https://thumbnail.image.rakuten.co.jp/@0_mall/book/cabinet/5536/9784594095536_3.jpg?_ex=64x64"}],"startTime":"","taxFlag":0}},{"Item":{"affiliateRate":"3.0","affiliateUrl":"","asurakuArea":"","asurakuClosingTime":"","asurakuFlag":0,"availability":1,"carrier":0,"catchcopy":"【楽天ブックスならいつでも送料無料】","creditCardFlag":1,"endTime":"","genreId":"208924","imageFlag":1,"itemCaption":"講談社 風間 俊介 講談社ディズニー シュプリーム ガイド トウキョウディズニーシーガイドブック ウィズ カザマシュンスケ コウダンシャ カザマ シュンスケ 発行年月：2023年07月26日 予約締切日：2023年05月23日 ページ数：96p サイズ：単行本 ISBN：9784065312117 本 旅行・留学・アウトドア テーマパーク","itemCode":"book:20977028","itemName":"Disney　Supreme　Guide　東京ディズニーシーガイドブック　with　風間俊介 [ 講談社 ]","itemPrice":"2200","itemUrl":"https://item.rakuten.co.jp/book/17522532/","mediumImageUrls":[{"imageUrl":"https://thumbnail.image.rakuten.co.jp/@0_mall/book/cabinet/2117/9784065312117.jpg?_ex=128x128"}],"pointRate":1,"pointRateEndTime":"","pointRateStartTime":"","postageFlag":0,"rank":6,"reviewAverage":"0.0","reviewCount":0,"shipOverseasArea":"","shipOverseasFlag":0,"shopAffiliateUrl":"","shopCode":"book","shopName":"楽天ブックス","shopOfTheYearFlag":0,"shopUrl":"https://www.rakuten.co.jp/book/","smallImageUrls":[{"imageUrl":"https://thumbnail.image.rakuten.co.jp/@0_mall/book/cabinet/2117/9784065312117.jpg?_ex=64x64"}],"startTime":"","taxFlag":0}},{"Item":{"affiliateRate":"3.0","affiliateUrl":"","asurakuArea":"","asurakuClosingTime":"","asurakuFlag":0,"availability":1,"carrier":0,"catchcopy":"【楽天ブックスならいつでも送料無料】","creditCardFlag":1,"endTime":"","genreId":"209031","imageFlag":1,"itemCaption":"万葉社発行年月：2022年10月 予約締切日：2023年04月21日 サイズ：単行本 ISBN：9784910481029 本 人文・思想・社会 文学 その他","itemCode":"book:20950582","itemName":"愛するよりも愛されたい","itemPrice":"999","itemUrl":"https://item.rakuten.co.jp/book/17495464/","mediumImageUrls":[{"imageUrl":"https://thumbnail.image.rakuten.co.jp/@0_mall/book/cabinet/1029/9784910481029_1_2.jpg?_ex=128x128"}],"pointRate":1,"pointRateEndTime":"","pointRateStartTime":"","postageFlag":0,"rank":7,"reviewAverage":"0.0","reviewCount":0,"shipOverseasArea":"","shipOverseasFlag":0,"shopAffiliateUrl":"","shopCode":"book","shopName":"楽天ブックス","shopOfTheYearFlag":0,"shopUrl":"https://www.rakuten.co.jp/book/","smallImageUrls":[{"imageUrl":"https://thumbnail.image.rakuten.co.jp/@0_mall/book/cabinet/1029/9784910481029_1_2.jpg?_ex=64x64"}],"startTime":"","taxFlag":0}},{"Item":{"affiliateRate":"3.0","affiliateUrl":"","asurakuArea":"","asurakuClosingTime":"","asurakuFlag":0,"availability":0,"carrier":0,"catchcopy":"【楽天ブックスならいつでも送料無料】","creditCardFlag":1,"endTime":"","genreId":"562214","imageFlag":1,"itemCaption":"稲葉　浩志 KADOKAWAデビュー 35周年 イナバコウジ B’z Bs ビーズ 松本孝弘 松本 稲葉浩志 稲葉 イナバコウシサクヒンシュウシアンセレクションバン イナバ　コウシ 発行年月：2023年05月29日 予約締切日：2023年01月24日 サイズ：単行本 ISBN：2100013375800 本 エンタメ・ゲーム タレント関連本 特製ポストカード","itemCode":"book:20877792","itemName":"【楽天ブックス限定特典】稲葉浩志作品集　シアン SINGLE & SOLO SELECTION(特製ポストカード) [ 稲葉　浩志 ]","itemPrice":"4180","itemUrl":"https://item.rakuten.co.jp/book/17409908/","mediumImageUrls":[{"imageUrl":"https://thumbnail.image.rakuten.co.jp/@0_mall/book/cabinet/5800/2100013375800_1_3.jpg?_ex=128x128"},{"imageUrl":"https://thumbnail.image.rakuten.co.jp/@0_mall/book/cabinet/5800/2100013375800_2_2.jpg?_ex=128x128"},{"imageUrl":"https://thumbnail.image.rakuten.co.jp/@0_mall/book/cabinet/5800/2100013375800_6.jpg?_ex=128x128"}],"pointRate":1,"pointRateEndTime":"","pointRateStartTime":"","postageFlag":0,"rank":8,"reviewAverage":"0.0","reviewCount":0,"shipOverseasArea":"","shipOverseasFlag":0,"shopAffiliateUrl":"","shopCode":"book","shopName":"楽天ブックス","shopOfTheYearFlag":0,"shopUrl":"https://www.rakuten.co.jp/book/","smallImageUrls":[{"imageUrl":"https://thumbnail.image.rakuten.co.jp/@0_mall/book/cabinet/5800/2100013375800_1_3.jpg?_ex=64x64"},{"imageUrl":"https://thumbnail.image.rakuten.co.jp/@0_mall/book/cabinet/5800/2100013375800_2_2.jpg?_ex=64x64"},{"imageUrl":"https://thumbnail.image.rakuten.co.jp/@0_mall/book/cabinet/5800/2100013375800_6.jpg?_ex=64x64"}],"startTime":"","taxFlag":0}},{"Item":{"affiliateRate":"3.0","affiliateUrl":"","asurakuArea":"","asurakuClosingTime":"","asurakuFlag":0,"availability":1,"carrier":0,"catchcopy":"【楽天ブックスならいつでも送料無料】","creditCardFlag":1,"endTime":"","genreId":"101934","imageFlag":1,"itemCaption":"ことばはどう生まれ、進化したか 中公新書　2756 今井むつみ 秋田喜美 中央公論新社ゲンゴノホンシツ イマイムツミ アキタキミ 発行年月：2023年05月24日 予約締切日：2023年04月03日 ページ数：304p サイズ：新書 ISBN：9784121027566 本 人文・思想・社会 言語学 新書 語学・学習参考書 新書 人文・思想・社会","itemCode":"book:20934970","itemName":"言語の本質 ことばはどう生まれ、進化したか （中公新書　2756） [ 今井むつみ ]","itemPrice":"1056","itemUrl":"https://item.rakuten.co.jp/book/17477153/","mediumImageUrls":[{"imageUrl":"https://thumbnail.image.rakuten.co.jp/@0_mall/book/cabinet/7566/9784121027566_1_2.jpg?_ex=128x128"},{"imageUrl":"https://thumbnail.image.rakuten.co.jp/@0_mall/book/cabinet/7566/9784121027566_2_2.jpg?_ex=128x128"}],"pointRate":1,"pointRateEndTime":"","pointRateStartTime":"","postageFlag":0,"rank":9,"reviewAverage":"0.0","reviewCount":0,"shipOverseasArea":"","shipOverseasFlag":0,"shopAffiliateUrl":"","shopCode":"book","shopName":"楽天ブックス","shopOfTheYearFlag":0,"shopUrl":"https://www.rakuten.co.jp/book/","smallImageUrls":[{"imageUrl":"https://thumbnail.image.rakuten.co.jp/@0_mall/book/cabinet/7566/9784121027566_1_2.jpg?_ex=64x64"},{"imageUrl":"https://thumbnail.image.rakuten.co.jp/@0_mall/book/cabinet/7566/9784121027566_2_2.jpg?_ex=64x64"}],"startTime":"","taxFlag":0}},{"Item":{"affiliateRate":"3.0","affiliateUrl":"","asurakuArea":"","asurakuClosingTime":"","asurakuFlag":0,"availability":0,"carrier":0,"catchcopy":"【楽天ブックスならいつでも送料無料】","creditCardFlag":1,"endTime":"","genreId":"562214","imageFlag":1,"itemCaption":"稲葉　浩志 KADOKAWAデビュー 35周年 イナバコウジ B’z Bs ビーズ 松本孝弘 松本 稲葉浩志 稲葉 イナバコウシサクヒンシュウ　シアン シングルアンドソロセレクション イナバ　コウシ 発行年月：2023年05月29日 予約締切日：2023年01月24日 ページ数：272p サイズ：単行本 ISBN：9784048975711 本 人文・思想・社会 文学 詩歌・俳諧 エンタメ・ゲーム タレント関連本","itemCode":"book:20877784","itemName":"稲葉浩志作品集　シアン SINGLE & SOLO SELECTION [ 稲葉　浩志 ]","itemPrice":"4180","itemUrl":"https://item.rakuten.co.jp/book/17409907/","mediumImageUrls":[{"imageUrl":"https://thumbnail.image.rakuten.co.jp/@0_mall/book/cabinet/5711/9784048975711_1_3.jpg?_ex=128x128"},{"imageUrl":"https://thumbnail.image.rakuten.co.jp/@0_mall/book/cabinet/5711/9784048975711_2_2.jpg?_ex=128x128"}],"pointRate":1,"pointRateEndTime":"","pointRateStartTime":"","postageFlag":0,"rank":10,"reviewAverage":"0.0","reviewCount":0,"shipOverseasArea":"","shipOverseasFlag":0,"shopAffiliateUrl":"","shopCode":"book","shopName":"楽天ブックス","shopOfTheYearFlag":0,"shopUrl":"https://www.rakuten.co.jp/book/","smallImageUrls":[{"imageUrl":"https://thumbnail.image.rakuten.co.jp/@0_mall/book/cabinet/5711/9784048975711_1_3.jpg?_ex=64x64"},{"imageUrl":"https://thumbnail.image.rakuten.co.jp/@0_mall/book/cabinet/5711/9784048975711_2_2.jpg?_ex=64x64"}],"startTime":"","taxFlag":0}},{"Item":{"affiliateRate":"3.0","affiliateUrl":"","asurakuArea":"群馬県/埼玉県/千葉県/東京都/神奈川県/新潟県/山梨県/長野県/岐阜県/静岡県/愛知県/三重県/滋賀県/宮城県/福島県/茨城県/栃木県","asurakuClosingTime":"12:00","asurakuFlag":1,"availability":1,"carrier":0,"catchcopy":"【楽天ブックスならいつでも送料無料】","creditCardFlag":1,"endTime":"","genreId":"112354","imageFlag":1,"itemCaption":"齋藤飛鳥 三瓶康友 講談社東京ドーム 乃木坂46 齋藤飛鳥 卒業 サイトウアスカ　シャシンシュウ　ミュージアム 発行年月：2023年05月24日 予約締切日：2023年04月10日 ISBN：9784065322932 本 写真集・タレント グラビアアイドル・タレント写真集 限定カバー ポストカード","itemCode":"book:20942097","itemName":"【楽天ブックス限定特典】齋藤飛鳥写真集　ミュージアム(限定カバー+ポストカード) [ 齋藤飛鳥 ]","itemPrice":"2200","itemUrl":"https://item.rakuten.co.jp/book/17484050/","mediumImageUrls":[{"imageUrl":"https://thumbnail.image.rakuten.co.jp/@0_mall/book/cabinet/2932/9784065322932_1_3.jpg?_ex=128x128"},{"imageUrl":"https://thumbnail.image.rakuten.co.jp/@0_mall/book/cabinet/2932/9784065322932_2_2.jpg?_ex=128x128"}],"pointRate":1,"pointRateEndTime":"","pointRateStartTime":"","postageFlag":0,"rank":11,"reviewAverage":"4.0","reviewCount":16,"shipOverseasArea":"","shipOverseasFlag":0,"shopAffiliateUrl":"","shopCode":"book","shopName":"楽天ブックス","shopOfTheYearFlag":0,"shopUrl":"https://www.rakuten.co.jp/book/","smallImageUrls":[{"imageUrl":"https://thumbnail.image.rakuten.co.jp/@0_mall/book/cabinet/2932/9784065322932_1_3.jpg?_ex=64x64"},{"imageUrl":"https://thumbnail.image.rakuten.co.jp/@0_mall/book/cabinet/2932/9784065322932_2_2.jpg?_ex=64x64"}],"startTime":"","taxFlag":0}},{"Item":{"affiliateRate":"3.0","affiliateUrl":"","asurakuArea":"","asurakuClosingTime":"","asurakuFlag":0,"availability":0,"carrier":0,"catchcopy":"【楽天ブックスならいつでも送料無料】","creditCardFlag":1,"endTime":"","genreId":"112325","imageFlag":1,"itemCaption":"アレン 主婦の友社イチニチイチマイアレンサマノオコトバトオシャシンブックサンロクロク アレン 発行年月：2023年03月27日 予約締切日：2023年03月15日 ページ数：0p サイズ：単行本 ISBN：9784073454953 本 カレンダー・手帳・家計簿 カレンダー タレント","itemCode":"book:20920292","itemName":"一日一枚 アレン様のお言葉とお写真BOOK366 [ アレン ]","itemPrice":"3300","itemUrl":"https://item.rakuten.co.jp/book/17460761/","mediumImageUrls":[{"imageUrl":"https://thumbnail.image.rakuten.co.jp/@0_mall/book/cabinet/4953/9784073454953_1_3.jpg?_ex=128x128"}],"pointRate":1,"pointRateEndTime":"","pointRateStartTime":"","postageFlag":0,"rank":12,"reviewAverage":"5.0","reviewCount":3,"shipOverseasArea":"","shipOverseasFlag":0,"shopAffiliateUrl":"","shopCode":"book","shopName":"楽天ブックス","shopOfTheYearFlag":0,"shopUrl":"https://www.rakuten.co.jp/book/","smallImageUrls":[{"imageUrl":"https://thumbnail.image.rakuten.co.jp/@0_mall/book/cabinet/4953/9784073454953_1_3.jpg?_ex=64x64"}],"startTime":"","taxFlag":0}},{"Item":{"affiliateRate":"3.0","affiliateUrl":"","asurakuArea":"","asurakuClosingTime":"","asurakuFlag":0,"availability":1,"carrier":0,"catchcopy":"【電子書籍なら、スマホ・パソコンの無料アプリで今すぐ読める！】","creditCardFlag":1,"endTime":"","genreId":"200528","imageFlag":1,"itemCaption":"＜p＞【巻頭カラー】累計280万部突破『マイホームヒーロー』鳥栖家を脅かすヤクザ・“志野”。その秘められた過去とはーー。 【巻中カラー】『パラレルパラダイス』祝・累計400万部突破！　計画は失敗し、ヤールヤーに再び取り込まれた陽太達。為す術なし・・・・！？　【表紙&巻頭グラビア】『本郷柚巴』感謝感謝の卒業前ラストグラビア！　写真集から蔵出しカットを特別公開やで！　【巻末グラビア】『くろがねさら』話題の美少女インフルエンサーが再び登場ーッ！　激バズBODYをご堪能あれ☆＜/p＞画面が切り替わりますので、しばらくお待ち下さい。 ※ご購入は、楽天kobo商品ページからお願いします。※切り替わらない場合は、こちら をクリックして下さい。 ※このページからは注文できません。","itemCode":"rakutenkobo-ebooks:22371987","itemName":"ヤングマガジン 2023年26号 [2023年5月29日発売]【電子書籍】[ 山川直輝 ]","itemPrice":"480","itemUrl":"https://item.rakuten.co.jp/rakutenkobo-ebooks/f14e24f3581735308dfc1db9a338175a/","mediumImageUrls":[{"imageUrl":"https://thumbnail.image.rakuten.co.jp/@0_mall/rakutenkobo-ebooks/cabinet/3788/2000013093788.jpg?_ex=128x128"}],"pointRate":1,"pointRateEndTime":"","pointRateStartTime":"","postageFlag":0,"rank":13,"reviewAverage":"0.0","reviewCount":0,"shipOverseasArea":"","shipOverseasFlag":0,"shopAffiliateUrl":"","shopCode":"rakutenkobo-ebooks","shopName":"楽天Kobo電子書籍ストア","shopOfTheYearFlag":0,"shopUrl":"https://www.rakuten.co.jp/rakutenkobo-ebooks/","smallImageUrls":[{"imageUrl":"https://thumbnail.image.rakuten.co.jp/@0_mall/rakutenkobo-ebooks/cabinet/3788/2000013093788.jpg?_ex=64x64"}],"startTime":"","taxFlag":0}},{"Item":{"affiliateRate":"3.0","affiliateUrl":"","asurakuArea":"","asurakuClosingTime":"","asurakuFlag":0,"availability":1,"carrier":0,"catchcopy":"【楽天ブックスならいつでも送料無料】","creditCardFlag":1,"endTime":"","genreId":"200472","imageFlag":1,"itemCaption":"ジャンプコミックス 尾田 栄一郎 集英社ワンピース ONEPIECE 106巻 106 107 最新 最新号 最新刊 わんぴーす ワンピース オダ エイイチロウ 発行年月：2023年07月04日 予約締切日：2023年05月18日 ページ数：208p サイズ：コミック ISBN：9784088836447 本 漫画（コミック） 少年 集英社 ジャンプC","itemCode":"book:20971294","itemName":"ONE PIECE 106 （ジャンプコミックス） [ 尾田 栄一郎 ]","itemPrice":"528","itemUrl":"https://item.rakuten.co.jp/book/17518281/","mediumImageUrls":[{"imageUrl":"https://thumbnail.image.rakuten.co.jp/@0_mall/book/cabinet/6447/9784088836447.gif?_ex=128x128"}],"pointRate":1,"pointRateEndTime":"","pointRateStartTime":"","postageFlag":0,"rank":14,"reviewAverage":"5.0","reviewCount":1,"shipOverseasArea":"","shipOverseasFlag":0,"shopAffiliateUrl":"","shopCode":"book","shopName":"楽天ブックス","shopOfTheYearFlag":0,"shopUrl":"https://www.rakuten.co.jp/book/","smallImageUrls":[{"imageUrl":"https://thumbnail.image.rakuten.co.jp/@0_mall/book/cabinet/6447/9784088836447.gif?_ex=64x64"}],"startTime":"","taxFlag":0}},{"Item":{"affiliateRate":"3.0","affiliateUrl":"","asurakuArea":"","asurakuClosingTime":"","asurakuFlag":0,"availability":1,"carrier":0,"catchcopy":"【楽天ブックスならいつでも送料無料】","creditCardFlag":1,"endTime":"","genreId":"101941","imageFlag":1,"itemCaption":"ヤングジャンプコミックス 赤坂 アカ 横槍 メンゴ 集英社全巻セット 【コミックセット】 全巻 セット 新品 コミックセット ＜全 漫画 全巻 コミックセット 大人買い オシノコ アカサカ アカ ヨコヤリ メンゴ 発行年月：2023年04月中旬 予約締切日：2023年03月29日 ISBN：2100013410655 本 セット本 コミックセット","itemCode":"book:20931723","itemName":"【全巻】推しの子 1-11巻セット （ヤングジャンプコミックス） [ 赤坂 アカ ]","itemPrice":"7667","itemUrl":"https://item.rakuten.co.jp/book/17473696/","mediumImageUrls":[{"imageUrl":"https://thumbnail.image.rakuten.co.jp/@0_mall/book/cabinet/0655/2100013410655.jpg?_ex=128x128"}],"pointRate":1,"pointRateEndTime":"","pointRateStartTime":"","postageFlag":0,"rank":15,"reviewAverage":"5.0","reviewCount":2,"shipOverseasArea":"","shipOverseasFlag":0,"shopAffiliateUrl":"","shopCode":"book","shopName":"楽天ブックス","shopOfTheYearFlag":0,"shopUrl":"https://www.rakuten.co.jp/book/","smallImageUrls":[{"imageUrl":"https://thumbnail.image.rakuten.co.jp/@0_mall/book/cabinet/0655/2100013410655.jpg?_ex=64x64"}],"startTime":"","taxFlag":0}},{"Item":{"affiliateRate":"3.0","affiliateUrl":"","asurakuArea":"","asurakuClosingTime":"","asurakuFlag":0,"availability":1,"carrier":0,"catchcopy":"","creditCardFlag":1,"endTime":"","genreId":"101942","imageFlag":1,"itemCaption":"CGWORLD vol.298（2023年5月10日発売）も話題の作品メイキングをたっぷりお届けします。","itemCode":"tributy:10000936","itemName":"CGWORLD (シージーワールド) 2023年 06月号 vol.298","itemPrice":"1760","itemUrl":"https://item.rakuten.co.jp/tributy/b0c22f22hg/","mediumImageUrls":[{"imageUrl":"https://thumbnail.image.rakuten.co.jp/@0_mall/tributy/cabinet/08275006/09840393/b0c22f22hg.jpg?_ex=128x128"}],"pointRate":1,"pointRateEndTime":"","pointRateStartTime":"","postageFlag":1,"rank":16,"reviewAverage":"0.0","reviewCount":0,"shipOverseasArea":"","shipOverseasFlag":0,"shopAffiliateUrl":"","shopCode":"tributy","shopName":"TRIBUTY","shopOfTheYearFlag":0,"shopUrl":"https://www.rakuten.co.jp/tributy/","smallImageUrls":[{"imageUrl":"https://thumbnail.image.rakuten.co.jp/@0_mall/tributy/cabinet/08275006/09840393/b0c22f22hg.jpg?_ex=64x64"}],"startTime":"","taxFlag":0}},{"Item":{"affiliateRate":"3.0","affiliateUrl":"","asurakuArea":"","asurakuClosingTime":"","asurakuFlag":0,"availability":1,"carrier":0,"catchcopy":"【楽天ブックスならいつでも送料無料】","creditCardFlag":1,"endTime":"","genreId":"101275","imageFlag":1,"itemCaption":"秋嶋亮 白馬社ニホンジン ガ ドレイ ニ ナラナイ タメニ アキシマ,リョウ 発行年月：2023年05月 予約締切日：2023年04月25日 ページ数：246p サイズ：単行本 ISBN：9784907872380 秋嶋亮（アキシマリョウ） 響堂雪乃より改名。全国紙系媒体の編集長を退任し社会学作家に転向。ブログ・マガジン「独りファシズム　Ver．0．3」を主宰し、グローバリゼーションをテーマに精力的な情報発信を続けている（本データはこの書籍が刊行された当時に掲載されていたものです） 第1章　戦争の時代に突入した（アメリカの公共事業としてのウクライナ戦争／金融軍産複合体VSプーチン政権という図式　ほか）／第2章　金融が平和を解体する（マスコミの詭弁が日本を弾圧国家にした／株価の動きを見れば戦争の目的が分かる　ほか）／第3章　カルトの支配は終わらない（投資銀行が日本にミサイルを発射する／日本を破滅させた人物が殺されて英雄になった　ほか）／第4章　理性が消失した日本の情景（狂気の国の政治家の言葉は空気よりも軽い／コロナ禍という地球規模のホワイトカラー犯罪　ほか）／第5章　無知による奴隷化というリアル（財政の私物化が最悪の円安をもたらした／「国債を恐れよ！」という絶叫の意味　ほか） 日本のリアルを告発する衝撃の対話編。 本 人文・思想・社会 社会科学","itemCode":"book:20954211","itemName":"日本人が奴隷にならないために [ 秋嶋亮 ]","itemPrice":"1760","itemUrl":"https://item.rakuten.co.jp/book/17498625/","mediumImageUrls":[{"imageUrl":"https://thumbnail.image.rakuten.co.jp/@0_mall/book/cabinet/2380/9784907872380_1_2.jpg?_ex=128x128"}],"pointRate":1,"pointRateEndTime":"","pointRateStartTime":"","postageFlag":0,"rank":17,"reviewAverage":"4.0","reviewCount":4,"shipOverseasArea":"","shipOverseasFlag":0,"shopAffiliateUrl":"","shopCode":"book","shopName":"楽天ブックス","shopOfTheYearFlag":0,"shopUrl":"https://www.rakuten.co.jp/book/","smallImageUrls":[{"imageUrl":"https://thumbnail.image.rakuten.co.jp/@0_mall/book/cabinet/2380/9784907872380_1_2.jpg?_ex=64x64"}],"startTime":"","taxFlag":0}},{"Item":{"affiliateRate":"3.0","affiliateUrl":"","asurakuArea":"","asurakuClosingTime":"","asurakuFlag":0,"availability":1,"carrier":0,"catchcopy":"【楽天ブックスならいつでも送料無料】","creditCardFlag":1,"endTime":"","genreId":"209306","imageFlag":1,"itemCaption":"ぴあ発行年月：2023年07月04日 予約締切日：2023年05月23日 ISBN：2100013455403 本 エンタメ・ゲーム 音楽 ロック・ポップス 限定絵柄ポストカード1枚","itemCode":"book:20977111","itemName":"【楽天ブックス限定特典】ぴあMUSIC COMPLEX(PMC)SPECIAL EDITION 3 Mrs. GREEN APPLE(限定絵柄ポストカード1枚)","itemPrice":"1650","itemUrl":"https://item.rakuten.co.jp/book/17521695/","mediumImageUrls":[{"imageUrl":"https://thumbnail.image.rakuten.co.jp/@0_mall/book/cabinet/5403/2100013455403_1_2.jpg?_ex=128x128"},{"imageUrl":"https://thumbnail.image.rakuten.co.jp/@0_mall/book/cabinet/5403/2100013455403_6.jpg?_ex=128x128"}],"pointRate":1,"pointRateEndTime":"","pointRateStartTime":"","postageFlag":0,"rank":18,"reviewAverage":"0.0","reviewCount":0,"shipOverseasArea":"","shipOverseasFlag":0,"shopAffiliateUrl":"","shopCode":"book","shopName":"楽天ブックス","shopOfTheYearFlag":0,"shopUrl":"https://www.rakuten.co.jp/book/","smallImageUrls":[{"imageUrl":"https://thumbnail.image.rakuten.co.jp/@0_mall/book/cabinet/5403/2100013455403_1_2.jpg?_ex=64x64"},{"imageUrl":"https://thumbnail.image.rakuten.co.jp/@0_mall/book/cabinet/5403/2100013455403_6.jpg?_ex=64x64"}],"startTime":"","taxFlag":0}},{"Item":{"affiliateRate":"3.0","affiliateUrl":"","asurakuArea":"群馬県/埼玉県/千葉県/東京都/神奈川県/新潟県/山梨県/長野県/岐阜県/静岡県/愛知県/三重県/滋賀県/宮城県/福島県/茨城県/栃木県","asurakuClosingTime":"12:00","asurakuFlag":1,"availability":1,"carrier":0,"catchcopy":"【楽天ブックスならいつでも送料無料】","creditCardFlag":1,"endTime":"","genreId":"209179","imageFlag":1,"itemCaption":"入門講習DVD付 藤瀧 和弘 ツールボックスニセンニジュウサンネンバンゼンブエデミテオボエルダイニシュデンキコウジシギノウシケンスイーットゴウカク フジタキ カズヒロ 発行年月：2023年03月10日 予約締切日：2023年02月07日 ページ数：254p サイズ：単行本 ISBN：9784910351056 付属資料：別冊1／DVD1 藤瀧和弘（フジタキカズヒロ） 東京都講師。電気工事士の試験情報サイト「かずわん先生の電気工事士技能試験教室」を運営（本データはこの書籍が刊行された当時に掲載されていたものです） 令和5年度技能試験公表候補問題／第1章　技能試験の実際／第2章　課題を理解する／第3章　複線図の描きかた／第4章　実技の基本作業／第5章　実践！作業シミュレート／第6章　候補問題　模範解答と解説 2023年候補問題の全想定解答！実際の試験で施工条件がどう出題されてもよいように、想定対策をポイント解説しています。候補全問の詳細作業手順付き！全問丁寧な作業手順付きだから、どの問題が出題されても対策は万全です。合格のための確実・最速作業手順を採用！試験に合格するために最も合理的で作業が速く確実に進められる方法で説明しています。携帯してどこででも学習できる書き込み式複線図練習帳付き！通勤や通学、昼休みなど、携帯していつでも候補問題の複線図の練習ができます。独学の人でも安心の基本作業DVD付き。DVDやスマホで観ながら練習できるので、すぐに上達できます。 本 科学・技術 工学 電気工学","itemCode":"book:20887426","itemName":"2023年版 ぜんぶ絵で見て覚える第2種電気工事士技能試験すい～っと合格 入門講習DVD付 [ 藤瀧 和弘 ]","itemPrice":"2090","itemUrl":"https://item.rakuten.co.jp/book/17422938/","mediumImageUrls":[{"imageUrl":"https://thumbnail.image.rakuten.co.jp/@0_mall/book/cabinet/1056/9784910351056_1_2.jpg?_ex=128x128"}],"pointRate":1,"pointRateEndTime":"","pointRateStartTime":"","postageFlag":0,"rank":19,"reviewAverage":"0.0","reviewCount":0,"shipOverseasArea":"","shipOverseasFlag":0,"shopAffiliateUrl":"","shopCode":"book","shopName":"楽天ブックス","shopOfTheYearFlag":0,"shopUrl":"https://www.rakuten.co.jp/book/","smallImageUrls":[{"imageUrl":"https://thumbnail.image.rakuten.co.jp/@0_mall/book/cabinet/1056/9784910351056_1_2.jpg?_ex=64x64"}],"startTime":"","taxFlag":0}},{"Item":{"affiliateRate":"3.0","affiliateUrl":"","asurakuArea":"","asurakuClosingTime":"","asurakuFlag":0,"availability":1,"carrier":0,"catchcopy":"【楽天ブックスならいつでも送料無料】","creditCardFlag":1,"endTime":"","genreId":"203063","imageFlag":1,"itemCaption":"NIKKO　MOOK 日本工業新聞社ニホン エイガ ナビ 発行年月：2023年06月01日 予約締切日：2023年05月24日 サイズ：ムックその他 ISBN：9784819153027 本 その他","itemCode":"book:20975689","itemName":"日本映画navi　vol．106","itemPrice":"1009","itemUrl":"https://item.rakuten.co.jp/book/17522831/","mediumImageUrls":[{"imageUrl":"https://thumbnail.image.rakuten.co.jp/@0_mall/book/cabinet/3027/9784819153027.gif?_ex=128x128"}],"pointRate":1,"pointRateEndTime":"","pointRateStartTime":"","postageFlag":0,"rank":20,"reviewAverage":"0.0","reviewCount":0,"shipOverseasArea":"","shipOverseasFlag":0,"shopAffiliateUrl":"","shopCode":"book","shopName":"楽天ブックス","shopOfTheYearFlag":0,"shopUrl":"https://www.rakuten.co.jp/book/","smallImageUrls":[{"imageUrl":"https://thumbnail.image.rakuten.co.jp/@0_mall/book/cabinet/3027/9784819153027.gif?_ex=64x64"}],"startTime":"","taxFlag":0}},{"Item":{"affiliateRate":"3.0","affiliateUrl":"","asurakuArea":"群馬県/埼玉県/千葉県/東京都/神奈川県/富山県/石川県/福井県/山梨県/静岡県/滋賀県/大阪府/兵庫県/奈良県/和歌山県/宮城県/山形県/福島県/茨城県/栃木県","asurakuClosingTime":"14:00","asurakuFlag":1,"availability":1,"carrier":0,"catchcopy":"","creditCardFlag":1,"endTime":"","genreId":"200472","imageFlag":1,"itemCaption":"2022年12月3日！いよいよ映画『THE FIRST SLAM DUNK』公開！ 【新装】全巻カバーイラストを作者・井上雄彦先生が描き下ろし!!／【再編】既刊ジャンプコミックス全31巻を「新装再編版」全20巻に再編したコミックス全巻セットをすぐにお届けいたします！ 【全冊分クリアカバー贈呈キャンペーン実施中 ※注文時オプションより選択ください】 作者 : 井上雄彦 出版社 : 集英社 あらすじ : 中学時代、50人の女の子にフラれた桜木花道。そんな男が、進学した湘北高校で赤木晴子に一目惚れ! 「バスケットは…お好きですか?」。この一言が、ワルで名高い花道の高校生活を変えることに!! ▼関連商品 : THE FIRST SLAM DUNK re:SOURCE スラムダンク『あれから10日後』完全版 SLAM DUNK スラムダンク[新装再編版] SLAM DUNK スラムダンク[新書版] SLAM DUNK スラムダンク[完全版] リアル バガボンド カメレオンジェイル 検索ワード: コミック、漫画、まんが、マンガ、アニメ、映画、セット、最新巻、単行本、漫画全巻、全巻セット、コミックセット SLAMDUNK新装再編版,スラムダンク,スラダン,漫画全巻セット, ※注意事項 大変人気な商品となっておりますので原則として一世帯一点までのご注文とさせていただきます。複数回のご注文が確認できた場合にはキャンセルさせていただく場合がございます。SLAMDUNK 新装再編版なら、漫画・コミック全巻大人買い専門書店の漫画全巻ドットコム","itemCode":"mangazenkan:10241277","itemName":"[新品/あす楽]スラムダンク SLAM DUNK 新装再編版(全20巻) 全巻セット","itemPrice":"13255","itemUrl":"https://item.rakuten.co.jp/mangazenkan/m9780491352/","mediumImageUrls":[{"imageUrl":"https://thumbnail.image.rakuten.co.jp/@0_mall/mangazenkan/cabinet/syncip_0044/m9780491352_ra_s.jpg?_ex=128x128"}],"pointRate":3,"pointRateEndTime":"2023-06-04 10:59","pointRateStartTime":"2023-05-29 17:00","postageFlag":0,"rank":21,"reviewAverage":"4.79","reviewCount":392,"shipOverseasArea":"アルゼンチン/オーストリア/オーストラリア/ベルギー/ブラジル/カナダ/スイス/中国/ドイツ/デンマーク/スペイン/フランス/英国/ギリシャ/香港/インドネシア/インド/イタリア/韓国/モロッコ/メキシコ/マレーシア/オランダ/ニュージーランド/フィリピン/ポーランド/ポルトガル/ロシア/スウェーデン/シンガポール/タイ/トルコ/台湾/アメリカ/ベトナム","shipOverseasFlag":1,"shopAffiliateUrl":"","shopCode":"mangazenkan","shopName":"漫画全巻ドットコム 楽天市場店","shopOfTheYearFlag":0,"shopUrl":"https://www.rakuten.co.jp/mangazenkan/","smallImageUrls":[{"imageUrl":"https://thumbnail.image.rakuten.co.jp/@0_mall/mangazenkan/cabinet/syncip_0044/m9780491352_ra_s.jpg?_ex=64x64"}],"startTime":"","taxFlag":0}},{"Item":{"affiliateRate":"3.0","affiliateUrl":"","asurakuArea":"","asurakuClosingTime":"","asurakuFlag":0,"availability":1,"carrier":0,"catchcopy":"【電子書籍なら、スマホ・パソコンの無料アプリで今すぐ読める！】","creditCardFlag":1,"endTime":"","genreId":"200528","imageFlag":1,"itemCaption":"＜p＞●巻頭グラビア！絶対的ヒロイン降臨！『大原優乃』（オオハラユウノ）　＜br /＞ ●巻頭カラー！人生100年時代の必読作！『お別れホスピタル』沖田×華　＜br /＞ ●『マイホームアフロ田中』のりつけ雅春　＜br /＞ ●『二月の勝者-絶対合格の教室-』高瀬志帆　＜br /＞ ●『夢なし先生の進路指導』笠原真樹　＜br /＞ ●『土竜の唄』高橋のぼる　＜br /＞ ●『路傍のフジイ』鍋倉夫　＜br /＞ ●『九条の大罪』真鍋昌平　＜br /＞ ●『魔王がずっと見ている』野田宏＋ふくしま正保　＜br /＞ ●巻中カラー！占いの裏側を暴く話題作！『占い師星子』岬ミミコ　＜br /＞ ●『往生際の意味を知れ！』米代恭　＜br /＞ ●『生きてるうちに推してくれ』丹羽庭　＜br /＞ ●巻中カラー！単行本続々重版！『ひらやすみ』真造圭伍　＜br /＞ ●『ハナイケル-川北高校華道部-』山田はまち　＜br /＞ ●『レ・セルバン』濱田浩輔　＜br /＞ ●巻中カラー！新章突入！『健康で文化的な最低限度の生活』柏木ハルコ　＜br /＞ ●『ダンス・ダンス・ダンスール』ジョージ朝倉　＜br /＞ ●『駅伝男子プロジェクト』高橋しん　＜br /＞ ●『忘却のサチコ』阿部潤　＜br /＞ ●『アカネノネ』矢田恵梨子　＜br /＞ ●『植物病理学は明日の君を願う』竹良実　＜br /＞ ●『風都探偵』石ノ森章太郎＋三条陸＋佐藤まさき　＜br /＞ ●『気まぐれコンセプト』ホイチョイ・プロ　＜br /＞ 　＜br /＞ ＊「週刊スピリッツ」デジタル版には、紙版の付録、特典等は含まれません。また、紙版と一部内容が異なる場合があります。ご了承ください。＜/p＞画面が切り替わりますので、しばらくお待ち下さい。 ※ご購入は、楽天kobo商品ページからお願いします。※切り替わらない場合は、こちら をクリックして下さい。 ※このページからは注文できません。","itemCode":"rakutenkobo-ebooks:22382409","itemName":"週刊ビッグコミックスピリッツ 2023年26号【デジタル版限定グラビア増量「大原優乃」】（2023年5月29日発売）【電子書籍】[ 週刊ビッグコミックスピリッツ編集部 ]","itemPrice":"450","itemUrl":"https://item.rakuten.co.jp/rakutenkobo-ebooks/62033931e2343569badd984ca28598e5/","mediumImageUrls":[{"imageUrl":"https://thumbnail.image.rakuten.co.jp/@0_mall/rakutenkobo-ebooks/cabinet/6746/2000013096746.jpg?_ex=128x128"}],"pointRate":1,"pointRateEndTime":"","pointRateStartTime":"","postageFlag":0,"rank":22,"reviewAverage":"0.0","reviewCount":0,"shipOverseasArea":"","shipOverseasFlag":0,"shopAffiliateUrl":"","shopCode":"rakutenkobo-ebooks","shopName":"楽天Kobo電子書籍ストア","shopOfTheYearFlag":0,"shopUrl":"https://www.rakuten.co.jp/rakutenkobo-ebooks/","smallImageUrls":[{"imageUrl":"https://thumbnail.image.rakuten.co.jp/@0_mall/rakutenkobo-ebooks/cabinet/6746/2000013096746.jpg?_ex=64x64"}],"startTime":"","taxFlag":0}},{"Item":{"affiliateRate":"3.0","affiliateUrl":"","asurakuArea":"群馬県/埼玉県/千葉県/東京都/神奈川県/新潟県/山梨県/長野県/岐阜県/静岡県/愛知県/三重県/滋賀県/宮城県/福島県/茨城県/栃木県","asurakuClosingTime":"12:00","asurakuFlag":1,"availability":1,"carrier":0,"catchcopy":"【楽天ブックスならいつでも送料無料】","creditCardFlag":1,"endTime":"","genreId":"209212","imageFlag":1,"itemCaption":"ビッグ コミックス 小林 有吾 小学館アオアシ コバヤシ ユウゴ 発行年月：2023年05月30日 予約締切日：2023年04月03日 ページ数：192p サイズ：コミック ISBN：9784098617050 本 漫画（コミック） 青年 小学館 ビッグC","itemCode":"book:20934777","itemName":"アオアシ（32） （ビッグ コミックス） [ 小林 有吾 ]","itemPrice":"715","itemUrl":"https://item.rakuten.co.jp/book/17476918/","mediumImageUrls":[{"imageUrl":"https://thumbnail.image.rakuten.co.jp/@0_mall/book/cabinet/7050/9784098617050_1_3.jpg?_ex=128x128"}],"pointRate":1,"pointRateEndTime":"","pointRateStartTime":"","postageFlag":0,"rank":23,"reviewAverage":"5.0","reviewCount":1,"shipOverseasArea":"","shipOverseasFlag":0,"shopAffiliateUrl":"","shopCode":"book","shopName":"楽天ブックス","shopOfTheYearFlag":0,"shopUrl":"https://www.rakuten.co.jp/book/","smallImageUrls":[{"imageUrl":"https://thumbnail.image.rakuten.co.jp/@0_mall/book/cabinet/7050/9784098617050_1_3.jpg?_ex=64x64"}],"startTime":"","taxFlag":0}},{"Item":{"affiliateRate":"3.0","affiliateUrl":"","asurakuArea":"","asurakuClosingTime":"","asurakuFlag":0,"availability":1,"carrier":0,"catchcopy":"【電子書籍なら、スマホ・パソコンの無料アプリで今すぐ読める！】","creditCardFlag":1,"endTime":"","genreId":"209212","imageFlag":1,"itemCaption":"＜p＞異世界に転生し、あらゆる物事に陰から介入し実力を示す「陰の実力者」設定をエンジョイしているシド。ローズ王女結婚の噂を聞き、結婚阻止計画を実行するべくオリアナ王国の城に潜入する。シドはローズに、王妃ではなく光の覇王になってほしかったのだ。なぜなら光あるところに「陰の実力者」はより濃く存在できるからーー！いつも通りの勘違いも、いつも通りに炸裂する異世界異聞奇譚、信念の第11巻!!＜/p＞画面が切り替わりますので、しばらくお待ち下さい。 ※ご購入は、楽天kobo商品ページからお願いします。※切り替わらない場合は、こちら をクリックして下さい。 ※このページからは注文できません。","itemCode":"rakutenkobo-ebooks:22335355","itemName":"陰の実力者になりたくて！　（11）【電子書籍】[ 坂野　杏梨 ]","itemPrice":"748","itemUrl":"https://item.rakuten.co.jp/rakutenkobo-ebooks/54b9f61d28ec3026b280475f4122cb23/","mediumImageUrls":[{"imageUrl":"https://thumbnail.image.rakuten.co.jp/@0_mall/rakutenkobo-ebooks/cabinet/2282/2000012912282.jpg?_ex=128x128"}],"pointRate":1,"pointRateEndTime":"","pointRateStartTime":"","postageFlag":0,"rank":24,"reviewAverage":"4.0","reviewCount":1,"shipOverseasArea":"","shipOverseasFlag":0,"shopAffiliateUrl":"","shopCode":"rakutenkobo-ebooks","shopName":"楽天Kobo電子書籍ストア","shopOfTheYearFlag":0,"shopUrl":"https://www.rakuten.co.jp/rakutenkobo-ebooks/","smallImageUrls":[{"imageUrl":"https://thumbnail.image.rakuten.co.jp/@0_mall/rakutenkobo-ebooks/cabinet/2282/2000012912282.jpg?_ex=64x64"}],"startTime":"","taxFlag":0}},{"Item":{"affiliateRate":"3.0","affiliateUrl":"","asurakuArea":"","asurakuClosingTime":"","asurakuFlag":0,"availability":1,"carrier":0,"catchcopy":"【楽天ブックスならいつでも送料無料】","creditCardFlag":1,"endTime":"2023-07-03 02:59","genreId":"112354","imageFlag":1,"itemCaption":"八木 勇征 田尾 沙織 ワニブックス 販売スケジュールは商品ページをご確認くださいヤギ　ユウセイ　シャシンシュウ　コンタクト ヤギユウセイ タオサオリ 発行年月：2023年04月26日 予約締切日：2023年02月16日 ページ数：192 サイズ：単行本 ISBN：9784847084867 本 写真集・タレント グラビアアイドル・タレント写真集 限定カバー","itemCode":"book:20902206","itemName":"【楽天ブックス限定特典】八木勇征 1st 写真集 『 CONTACT 』 特別限定版(限定カバー) [ 八木 勇征 ]","itemPrice":"2970","itemUrl":"https://item.rakuten.co.jp/book/17434022/","mediumImageUrls":[{"imageUrl":"https://thumbnail.image.rakuten.co.jp/@0_mall/book/cabinet/4867/9784847084867_1_2.jpg?_ex=128x128"},{"imageUrl":"https://thumbnail.image.rakuten.co.jp/@0_mall/book/cabinet/4867/9784847084867_2.jpg?_ex=128x128"}],"pointRate":1,"pointRateEndTime":"","pointRateStartTime":"","postageFlag":0,"rank":25,"reviewAverage":"0.0","reviewCount":0,"shipOverseasArea":"","shipOverseasFlag":0,"shopAffiliateUrl":"","shopCode":"book","shopName":"楽天ブックス","shopOfTheYearFlag":0,"shopUrl":"https://www.rakuten.co.jp/book/","smallImageUrls":[{"imageUrl":"https://thumbnail.image.rakuten.co.jp/@0_mall/book/cabinet/4867/9784847084867_1_2.jpg?_ex=64x64"},{"imageUrl":"https://thumbnail.image.rakuten.co.jp/@0_mall/book/cabinet/4867/9784847084867_2.jpg?_ex=64x64"}],"startTime":"2023-05-30 03:00","taxFlag":0}},{"Item":{"affiliateRate":"3.0","affiliateUrl":"","asurakuArea":"群馬県/埼玉県/千葉県/東京都/神奈川県/新潟県/山梨県/長野県/岐阜県/静岡県/愛知県/三重県/滋賀県/宮城県/福島県/茨城県/栃木県","asurakuClosingTime":"12:00","asurakuFlag":1,"availability":1,"carrier":0,"catchcopy":"【楽天ブックスならいつでも送料無料】","creditCardFlag":1,"endTime":"","genreId":"208876","imageFlag":1,"itemCaption":"小学館 小学館タッチペンデオトガキケル！ハジメテズカン1000 エイゴツキ ショウガクカン 発行年月：2020年06月17日 予約締切日：2020年05月29日 ページ数：68p サイズ：図鑑 ISBN：9784099416775 本 絵本・児童書・図鑑 絵本 絵本(日本）","itemCode":"book:20034188","itemName":"タッチペンで音が聞ける！はじめてずかん1000 英語つき [ 小学館 ]","itemPrice":"4928","itemUrl":"https://item.rakuten.co.jp/book/16353156/","mediumImageUrls":[{"imageUrl":"https://thumbnail.image.rakuten.co.jp/@0_mall/book/cabinet/6775/9784099416775.jpg?_ex=128x128"},{"imageUrl":"https://thumbnail.image.rakuten.co.jp/@0_mall/book/cabinet/6775/9784099416775_2.jpg?_ex=128x128"},{"imageUrl":"https://thumbnail.image.rakuten.co.jp/@0_mall/book/cabinet/6775/9784099416775_3.jpg?_ex=128x128"}],"pointRate":1,"pointRateEndTime":"","pointRateStartTime":"","postageFlag":0,"rank":26,"reviewAverage":"4.7","reviewCount":870,"shipOverseasArea":"","shipOverseasFlag":0,"shopAffiliateUrl":"","shopCode":"book","shopName":"楽天ブックス","shopOfTheYearFlag":0,"shopUrl":"https://www.rakuten.co.jp/book/","smallImageUrls":[{"imageUrl":"https://thumbnail.image.rakuten.co.jp/@0_mall/book/cabinet/6775/9784099416775.jpg?_ex=64x64"},{"imageUrl":"https://thumbnail.image.rakuten.co.jp/@0_mall/book/cabinet/6775/9784099416775_2.jpg?_ex=64x64"},{"imageUrl":"https://thumbnail.image.rakuten.co.jp/@0_mall/book/cabinet/6775/9784099416775_3.jpg?_ex=64x64"}],"startTime":"","taxFlag":0}},{"Item":{"affiliateRate":"3.0","affiliateUrl":"","asurakuArea":"","asurakuClosingTime":"","asurakuFlag":0,"availability":1,"carrier":0,"catchcopy":"【楽天ブックスならいつでも送料無料】","creditCardFlag":1,"endTime":"","genreId":"200520","imageFlag":1,"itemCaption":"人の上に立ち続けるための思考法 安藤広大 ダイヤモンド社トニカクシクミカ アンドウコウダイ 発行年月：2023年06月01日 予約締切日：2023年03月15日 ページ数：320p サイズ：単行本 ISBN：9784478117743 本 ビジネス・経済・就職 経営 経営戦略・管理","itemCode":"book:20920348","itemName":"とにかく仕組み化 人の上に立ち続けるための思考法 [ 安藤広大 ]","itemPrice":"1760","itemUrl":"https://item.rakuten.co.jp/book/17460711/","mediumImageUrls":[{"imageUrl":"https://thumbnail.image.rakuten.co.jp/@0_mall/book/cabinet/7743/9784478117743_1_2.jpg?_ex=128x128"}],"pointRate":1,"pointRateEndTime":"","pointRateStartTime":"","postageFlag":0,"rank":27,"reviewAverage":"0.0","reviewCount":0,"shipOverseasArea":"","shipOverseasFlag":0,"shopAffiliateUrl":"","shopCode":"book","shopName":"楽天ブックス","shopOfTheYearFlag":0,"shopUrl":"https://www.rakuten.co.jp/book/","smallImageUrls":[{"imageUrl":"https://thumbnail.image.rakuten.co.jp/@0_mall/book/cabinet/7743/9784478117743_1_2.jpg?_ex=64x64"}],"startTime":"","taxFlag":0}},{"Item":{"affiliateRate":"3.0","affiliateUrl":"","asurakuArea":"","asurakuClosingTime":"","asurakuFlag":0,"availability":1,"carrier":0,"catchcopy":"【電子書籍なら、スマホ・パソコンの無料アプリで今すぐ読める！】","creditCardFlag":1,"endTime":"","genreId":"101941","imageFlag":1,"itemCaption":"＜p＞度重なる魔族の襲撃をはねのけ、クレアの王都への護衛を完遂したロイドたち一行。王の歓待を受け、一息ついたのも束の間、今度は他の勇者や冒険者たちとダンジョン攻略に！？ロイドの師匠・マーリンのファンという獣人女子・リョウエンや、ちょっと色々こじらせ気味なゴスロリ黒魔導師・シノなど、新キャラも充実で送る無自覚チート白魔導師の物語、第5巻！＜/p＞画面が切り替わりますので、しばらくお待ち下さい。 ※ご購入は、楽天kobo商品ページからお願いします。※切り替わらない場合は、こちら をクリックして下さい。 ※このページからは注文できません。","itemCode":"rakutenkobo-ebooks:22374689","itemName":"勇者パーティーを追放された白魔導師、Sランク冒険者に拾われる〜この白魔導師が規格外すぎる〜（コミック） ： 5【電子書籍】[ 椋野わさび ]","itemPrice":"748","itemUrl":"https://item.rakuten.co.jp/rakutenkobo-ebooks/da628dd5136e33608c2bf64b03137f53/","mediumImageUrls":[{"imageUrl":"https://thumbnail.image.rakuten.co.jp/@0_mall/rakutenkobo-ebooks/cabinet/6943/2000013096943.jpg?_ex=128x128"}],"pointRate":1,"pointRateEndTime":"","pointRateStartTime":"","postageFlag":0,"rank":28,"reviewAverage":"0.0","reviewCount":0,"shipOverseasArea":"","shipOverseasFlag":0,"shopAffiliateUrl":"","shopCode":"rakutenkobo-ebooks","shopName":"楽天Kobo電子書籍ストア","shopOfTheYearFlag":0,"shopUrl":"https://www.rakuten.co.jp/rakutenkobo-ebooks/","smallImageUrls":[{"imageUrl":"https://thumbnail.image.rakuten.co.jp/@0_mall/rakutenkobo-ebooks/cabinet/6943/2000013096943.jpg?_ex=64x64"}],"startTime":"","taxFlag":0}},{"Item":{"affiliateRate":"3.0","affiliateUrl":"","asurakuArea":"群馬県/埼玉県/千葉県/東京都/神奈川県/新潟県/山梨県/長野県/岐阜県/静岡県/愛知県/三重県/滋賀県/宮城県/福島県/茨城県/栃木県","asurakuClosingTime":"12:00","asurakuFlag":1,"availability":1,"carrier":0,"catchcopy":"【楽天ブックスならいつでも送料無料】","creditCardFlag":1,"endTime":"","genreId":"216751","imageFlag":1,"itemCaption":"イマジカインフォス 主婦の友社エスカワイイメンニセンニジュウサンサマー イマジカインフォス 発行年月：2023年05月29日 予約締切日：2023年04月18日 ページ数：86p サイズ：ムックその他 ISBN：9784074552559 本 美容・暮らし・健康・料理 ファッション・美容 その他","itemCode":"book:20946910","itemName":"S Cawaii! MEN 2023 SUMMER [ イマジカインフォス ]","itemPrice":"1650","itemUrl":"https://item.rakuten.co.jp/book/17490883/","mediumImageUrls":[{"imageUrl":"https://thumbnail.image.rakuten.co.jp/@0_mall/book/cabinet/2559/9784074552559_1_3.jpg?_ex=128x128"}],"pointRate":1,"pointRateEndTime":"","pointRateStartTime":"","postageFlag":0,"rank":29,"reviewAverage":"0.0","reviewCount":0,"shipOverseasArea":"","shipOverseasFlag":0,"shopAffiliateUrl":"","shopCode":"book","shopName":"楽天ブックス","shopOfTheYearFlag":0,"shopUrl":"https://www.rakuten.co.jp/book/","smallImageUrls":[{"imageUrl":"https://thumbnail.image.rakuten.co.jp/@0_mall/book/cabinet/2559/9784074552559_1_3.jpg?_ex=64x64"}],"startTime":"","taxFlag":0}},{"Item":{"affiliateRate":"3.0","affiliateUrl":"","asurakuArea":"群馬県/埼玉県/千葉県/東京都/神奈川県/新潟県/山梨県/長野県/岐阜県/静岡県/愛知県/三重県/滋賀県/宮城県/福島県/茨城県/栃木県","asurakuClosingTime":"12:00","asurakuFlag":1,"availability":1,"carrier":0,"catchcopy":"【楽天ブックスならいつでも送料無料】","creditCardFlag":1,"endTime":"","genreId":"208815","imageFlag":1,"itemCaption":"SB新書 出口保行 SBクリエイティブハンザイシンリガクシャガオシエルコドモヲノロウコトバスクウコトバ デグチヤスユキ 発行年月：2022年08月09日 予約締切日：2022年06月06日 ページ数：224p サイズ：新書 ISBN：9784815616533 出口保行（デグチヤスユキ） 犯罪心理学者。1985年に東京学芸大学大学院教育学研究科発達心理学講座を修了し同年国家公務員上級心理職として法務省に入省。以後全国の少年鑑別所、刑務所、拘置所で犯罪者を心理学的に分析する資質鑑別に従事。心理分析した犯罪者は1万人を超える。その他、法務省矯正局、（財）矯正協会附属中央研究所出向、法務省法務大臣官房秘書課国際室勤務等を経て、2007年法務省法務総合研究所研究部室長研究官を最後に退官し、東京未来大学こども心理学部教授に着任。2013年からは同学部長を務める。現在、フジテレビ「全力！脱力タイムズ」にレギュラー出演しているほか、各局報道・情報番組において犯罪解説等を行っている（本データはこの書籍が刊行された当時に掲載されていたものです） はじめに　法務省で出会った1万人の犯罪者たちに学んだこと／序章　「よかれと思って」は親の自己満足／第1章　「みんなと仲良く」が個性を破壊する／第2章　「早くしなさい」が先を読む力を破壊する／第3章　「頑張りなさい」が意欲を破壊する／第4章　「何度言ったらわかるの」が自己肯定感を破壊する／第5章　「勉強しなさい」が信頼関係を破壊する／第6章　「気をつけて！」が共感性を破壊する／終章　子どもを伸ばす親の愛情 1万人の犯罪者・非行少年を心理分析してわかったこと。それは、虐待や育児放棄、貧困といったわかりやすい問題だけが、犯罪や非行につながるのではない、ということ。実は、親がよかれと思って投げかけた言葉が「呪い」となって子どもを思わぬ方向に導いてしまう。子どもの可能性を潰さずに伸ばす子育ては、どのように実現できるのか。犯罪心理学者が解説する新・子育て論。犯罪者・非行少年の事例とともに紹介する。 本 人文・思想・社会 教育・福祉 教育 人文・思想・社会 教育・福祉 社会教育 新書 美容・暮らし・健康・料理","itemCode":"book:20689602","itemName":"犯罪心理学者が教える子どもを呪う言葉・救う言葉 （SB新書） [ 出口保行 ]","itemPrice":"990","itemUrl":"https://item.rakuten.co.jp/book/17180873/","mediumImageUrls":[{"imageUrl":"https://thumbnail.image.rakuten.co.jp/@0_mall/book/cabinet/6533/9784815616533_1_5.jpg?_ex=128x128"},{"imageUrl":"https://thumbnail.image.rakuten.co.jp/@0_mall/book/cabinet/6533/9784815616533_2_4.jpg?_ex=128x128"},{"imageUrl":"https://thumbnail.image.rakuten.co.jp/@0_mall/book/cabinet/6533/9784815616533_3_3.jpg?_ex=128x128"}],"pointRate":1,"pointRateEndTime":"","pointRateStartTime":"","postageFlag":0,"rank":30,"reviewAverage":"4.83","reviewCount":18,"shipOverseasArea":"","shipOverseasFlag":0,"shopAffiliateUrl":"","shopCode":"book","shopName":"楽天ブックス","shopOfTheYearFlag":0,"shopUrl":"https://www.rakuten.co.jp/book/","smallImageUrls":[{"imageUrl":"https://thumbnail.image.rakuten.co.jp/@0_mall/book/cabinet/6533/9784815616533_1_5.jpg?_ex=64x64"},{"imageUrl":"https://thumbnail.image.rakuten.co.jp/@0_mall/book/cabinet/6533/9784815616533_2_4.jpg?_ex=64x64"},{"imageUrl":"https://thumbnail.image.rakuten.co.jp/@0_mall/book/cabinet/6533/9784815616533_3_3.jpg?_ex=64x64"}],"startTime":"","taxFlag":0}}],"lastBuildDate":"Tue, 30 May 2023 00:00:00 +0900","title":"【楽天市場】ランキング市場 【本・雑誌・コミック】"}