{"lat":34.7338,"lon":135.5014,"timezone":"Asia/Tokyo","timezone_offset":32400,"current":{"dt":1677533354,"sunrise":1677533385,"sunset":1677574317,"temp":2.33,"feels_like":0.19,"pressure":1031,"humidity":77,"dew_point":-1.13,"uvi":0,"clouds":0,"visibility":10000,"wind_speed":2.06,"wind_deg":310,"weather":[{"id":800,"main":"Clear","description":"晴天","icon":"01n"}]},"hourly":[{"dt":1677531600,"temp":2.33,"feels_like":2.33,"pressure":1031,"humidity":77,"dew_point":-1.13,"uvi":0,"clouds":0,"visibility":10000,"wind_speed":1.22,"wind_deg":137,"wind_gust":1.24,"weather":[{"id":800,"main":"Clear","description":"晴天","icon":"01n"}],"pop":0},{"dt":1677535200,"temp":3,"feels_like":3,"pressure":1031,"humidity":73,"dew_point":-1.2,"uvi":0.17,"clouds":0,"visibility":10000,"wind_speed":1.21,"wind_deg":137,"wind_gust":1.23,"weather":[{"id":800,"main":"Clear","description":"晴天","icon":"01d"}],"pop":0},{"dt":1677538800,"temp":4.13,"feels_like":4.13,"pressure":1031,"humidity":68,"dew_point":-1.09,"uvi":0.77,"clouds":0,"visibility":10000,"wind_speed":1.08,"wind_deg":142,"wind_gust":1.33,"weather":[{"id":800,"main":"Clear","description":"晴天","icon":"01d"}],"pop":0},{"dt":1677542400,"temp":5.94,"feels_like":5.94,"pressure":1032,"humidity":61,"dew_point":-0.88,"uvi":1.96,"clouds":0,"visibility":10000,"wind_speed":1.07,"wind_deg":174,"wind_gust":1.89,"weather":[{"id":800,"main":"Clear","description":"晴天","icon":"01d"}],"pop":0},{"dt":1677546000,"temp":8.53,"feels_like":7.22,"pressure":1032,"humidity":57,"dew_point":0.51,"uvi":3.43,"clouds":0,"visibility":10000,"wind_speed":2.32,"wind_deg":222,"wind_gust":5.65,"weather":[{"id":800,"main":"Clear","description":"晴天","icon":"01d"}],"pop":0},{"dt":1677549600,"temp":11.88,"feels_like":10.53,"pressure":1031,"humidity":54,"dew_point":2.66,"uvi":4.61,"clouds":0,"visibility":10000,"wind_speed":4,"wind_deg":227,"wind_gust":7.03,"weather":[{"id":800,"main":"Clear","description":"晴天","icon":"01d"}],"pop":0},{"dt":1677553200,"temp":13.2,"feels_like":11.91,"pressure":1030,"humidity":51,"dew_point":2.99,"uvi":5.05,"clouds":0,"visibility":10000,"wind_speed":5.13,"wind_deg":238,"wind_gust":7.55,"weather":[{"id":800,"main":"Clear","description":"晴天","icon":"01d"}],"pop":0},{"dt":1677556800,"temp":13.7,"feels_like":12.41,"pressure":1029,"humidity":49,"dew_point":3.08,"uvi":4.57,"clouds":1,"visibility":10000,"wind_speed":6.15,"wind_deg":240,"wind_gust":8.34,"weather":[{"id":800,"main":"Clear","description":"晴天","icon":"01d"}],"pop":0},{"dt":1677560400,"temp":14.04,"feels_like":12.75,"pressure":1029,"humidity":48,"dew_point":3.1,"uvi":3.35,"clouds":1,"visibility":10000,"wind_speed":6.7,"wind_deg":238,"wind_gust":9.09,"weather":[{"id":800,"main":"Clear","description":"晴天","icon":"01d"}],"pop":0},{"dt":1677564000,"temp":14.32,"feels_like":13.06,"pressure":1028,"humidity":48,"dew_point":3.2,"uvi":1.89,"clouds":1,"visibility":10000,"wind_speed":7.03,"wind_deg":235,"wind_gust":9.09,"weather":[{"id":800,"main":"Clear","description":"晴天","icon":"01d"}],"pop":0},{"dt":1677567600,"temp":14.08,"feels_like":12.82,"pressure":1028,"humidity":49,"dew_point":3.42,"uvi":0.75,"clouds":0,"visibility":10000,"wind_speed":6.79,"wind_deg":237,"wind_gust":8.41,"weather":[{"id":800,"main":"Clear","description":"晴天","icon":"01d"}],"pop":0},{"dt":1677571200,"temp":13.52,"feels_like":12.31,"pressure":1028,"humidity":53,"dew_point":3.82,"uvi":0.15,"clouds":0,"visibility":10000,"wind_speed":6.18,"wind_deg":236,"wind_gust":7.72,"weather":[{"id":800,"main":"Clear","description":"晴天","icon":"01d"}],"pop":0},{"dt":1677574800,"temp":12.76,"feels_like":11.66,"pressure":1028,"humidity":60,"dew_point":4.86,"uvi":0,"clouds":0,"visibility":10000,"wind_speed":5.23,"wind_deg":236,"wind_gust":7.65,"weather":[{"id":800,"main":"Clear","description":"晴天","icon":"01n"}],"pop":0},{"dt":1677578400,"temp":12.36,"feels_like":11.3,"pressure":1028,"humidity":63,"dew_point":5.28,"uvi":0,"clouds":0,"visibility":10000,"wind_speed":4.76,"wind_deg":231,"wind_gust":7.87,"weather":[{"id":800,"main":"Clear","description":"晴天","icon":"01n"}],"pop":0},{"dt":1677582000,"temp":11.78,"feels_like":10.76,"pressure":1028,"humidity":67,"dew_point":5.56,"uvi":0,"clouds":0,"visibility":10000,"wind_speed":4.79,"wind_deg":225,"wind_gust":8.66,"weather":[{"id":800,"main":"Clear","description":"晴天","icon":"01n"}],"pop":0},{"dt":1677585600,"temp":11.42,"feels_like":10.37,"pressure":1028,"humidity":67,"dew_point":5.25,"uvi":0,"clouds":0,"visibility":10000,"wind_speed":4.57,"wind_deg":218,"wind_gust":9.26,"weather":[{"id":800,"main":"Clear","description":"晴天","icon":"01n"}],"pop":0},{"dt":1677589200,"temp":11.02,"feels_like":9.9,"pressure":1028,"humidity":66,"dew_point":4.67,"uvi":0,"clouds":0,"visibility":10000,"wind_speed":3.97,"wind_deg":210,"wind_gust":9.3,"weather":[{"id":800,"main":"Clear","description":"晴天","icon":"01n"}],"pop":0},{"dt":1677592800,"temp":10.49,"feels_like":9.37,"pressure":1027,"humidity":68,"dew_point":4.53,"uvi":0,"clouds":0,"visibility":10000,"wind_speed":3.19,"wind_deg":211,"wind_gust":7,"weather":[{"id":800,"main":"Clear","description":"晴天","icon":"01n"}],"pop":0},{"dt":1677596400,"temp":10.06,"feels_like":8.98,"pressure":1027,"humidity":71,"dew_point":4.71,"uvi":0,"clouds":0,"visibility":10000,"wind_speed":2.69,"wind_deg":203,"wind_gust":5.12,"weather":[{"id":800,"main":"Clear","description":"晴天","icon":"01n"}],"pop":0},{"dt":1677600000,"temp":9.61,"feels_like":8.29,"pressure":1027,"humidity":73,"dew_point":4.71,"uvi":0,"clouds":0,"visibility":10000,"wind_speed":2.6,"wind_deg":198,"wind_gust":5.15,"weather":[{"id":800,"main":"Clear","description":"晴天","icon":"01n"}],"pop":0},{"dt":1677603600,"temp":9.18,"feels_like":8.3,"pressure":1027,"humidity":74,"dew_point":4.57,"uvi":0,"clouds":1,"visibility":10000,"wind_speed":1.93,"wind_deg":193,"wind_gust":3.33,"weather":[{"id":800,"main":"Clear","description":"晴天","icon":"01n"}],"pop":0},{"dt":1677607200,"temp":8.92,"feels_like":8.24,"pressure":1026,"humidity":75,"dew_point":4.49,"uvi":0,"clouds":17,"visibility":10000,"wind_speed":1.67,"wind_deg":194,"wind_gust":1.99,"weather":[{"id":801,"main":"Clouds","description":"薄い雲","icon":"02n"}],"pop":0},{"dt":1677610800,"temp":8.72,"feels_like":8.72,"pressure":1026,"humidity":75,"dew_point":4.31,"uvi":0,"clouds":100,"visibility":10000,"wind_speed":1.08,"wind_deg":185,"wind_gust":1.24,"weather":[{"id":804,"main":"Clouds","description":"厚い雲","icon":"04n"}],"pop":0},{"dt":1677614400,"temp":8.66,"feels_like":8.66,"pressure":1026,"humidity":75,"dew_point":4.22,"uvi":0,"clouds":100,"visibility":10000,"wind_speed":1.13,"wind_deg":179,"wind_gust":1.25,"weather":[{"id":804,"main":"Clouds","description":"厚い雲","icon":"04n"}],"pop":0},{"dt":1677618000,"temp":8.4,"feels_like":8.4,"pressure":1026,"humidity":76,"dew_point":4.22,"uvi":0,"clouds":100,"visibility":10000,"wind_speed":0.81,"wind_deg":166,"wind_gust":0.95,"weather":[{"id":804,"main":"Clouds","description":"厚い雲","icon":"04n"}],"pop":0},{"dt":1677621600,"temp":8.3,"feels_like":7.79,"pressure":1026,"humidity":76,"dew_point":4.12,"uvi":0.18,"clouds":92,"visibility":10000,"wind_speed":1.43,"wind_deg":148,"wind_gust":1.41,"weather":[{"id":804,"main":"Clouds","description":"厚い雲","icon":"04d"}],"pop":0},{"dt":1677625200,"temp":9.3,"feels_like":9.3,"pressure":1026,"humidity":71,"dew_point":4.13,"uvi":0.81,"clouds":73,"visibility":10000,"wind_speed":0.95,"wind_deg":138,"wind_gust":1.24,"weather":[{"id":803,"main":"Clouds","description":"曇りがち","icon":"04d"}],"pop":0},{"dt":1677628800,"temp":10.74,"feels_like":9.57,"pressure":1026,"humidity":65,"dew_point":4.33,"uvi":2.05,"clouds":61,"visibility":10000,"wind_speed":1.12,"wind_deg":146,"wind_gust":1.72,"weather":[{"id":803,"main":"Clouds","description":"曇りがち","icon":"04d"}],"pop":0},{"dt":1677632400,"temp":12.28,"feels_like":11.08,"pressure":1025,"humidity":58,"dew_point":4.02,"uvi":3.49,"clouds":7,"visibility":10000,"wind_speed":1.7,"wind_deg":193,"wind_gust":3.04,"weather":[{"id":800,"main":"Clear","description":"晴天","icon":"01d"}],"pop":0},{"dt":1677636000,"temp":13.77,"feels_like":12.51,"pressure":1024,"humidity":50,"dew_point":3.16,"uvi":4.67,"clouds":9,"visibility":10000,"wind_speed":2.48,"wind_deg":227,"wind_gust":4.23,"weather":[{"id":800,"main":"Clear","description":"晴天","icon":"01d"}],"pop":0},{"dt":1677639600,"temp":14.96,"feels_like":13.66,"pressure":1023,"humidity":44,"dew_point":2.42,"uvi":5.12,"clouds":14,"visibility":10000,"wind_speed":3.19,"wind_deg":235,"wind_gust":5.31,"weather":[{"id":801,"main":"Clouds","description":"薄い雲","icon":"02d"}],"pop":0},{"dt":1677643200,"temp":15.51,"feels_like":14.19,"pressure":1022,"humidity":41,"dew_point":2.25,"uvi":4.12,"clouds":34,"visibility":10000,"wind_speed":3.8,"wind_deg":234,"wind_gust":5.37,"weather":[{"id":802,"main":"Clouds","description":"雲","icon":"03d"}],"pop":0},{"dt":1677646800,"temp":15.54,"feels_like":14.22,"pressure":1021,"humidity":41,"dew_point":2.05,"uvi":3.02,"clouds":47,"visibility":10000,"wind_speed":4.16,"wind_deg":236,"wind_gust":6.05,"weather":[{"id":802,"main":"Clouds","description":"雲","icon":"03d"}],"pop":0},{"dt":1677650400,"temp":15.57,"feels_like":14.23,"pressure":1020,"humidity":40,"dew_point":1.72,"uvi":1.71,"clouds":56,"visibility":10000,"wind_speed":4.04,"wind_deg":219,"wind_gust":6.65,"weather":[{"id":803,"main":"Clouds","description":"曇りがち","icon":"04d"}],"pop":0},{"dt":1677654000,"temp":15.65,"feels_like":14.45,"pressure":1019,"humidity":45,"dew_point":3.32,"uvi":0.55,"clouds":100,"visibility":10000,"wind_speed":5.82,"wind_deg":224,"wind_gust":8.76,"weather":[{"id":804,"main":"Clouds","description":"厚い雲","icon":"04d"}],"pop":0},{"dt":1677657600,"temp":15.23,"feels_like":14.06,"pressure":1018,"humidity":48,"dew_point":4.17,"uvi":0.12,"clouds":100,"visibility":10000,"wind_speed":5.48,"wind_deg":215,"wind_gust":8.8,"weather":[{"id":804,"main":"Clouds","description":"厚い雲","icon":"04d"}],"pop":0},{"dt":1677661200,"temp":14.81,"feels_like":13.76,"pressure":1018,"humidity":54,"dew_point":5.2,"uvi":0,"clouds":100,"visibility":10000,"wind_speed":5.97,"wind_deg":205,"wind_gust":11.19,"weather":[{"id":804,"main":"Clouds","description":"厚い雲","icon":"04n"}],"pop":0},{"dt":1677664800,"temp":14.1,"feels_like":13.13,"pressure":1018,"humidity":60,"dew_point":6.12,"uvi":0,"clouds":83,"visibility":10000,"wind_speed":6.92,"wind_deg":202,"wind_gust":13.67,"weather":[{"id":803,"main":"Clouds","description":"曇りがち","icon":"04n"}],"pop":0},{"dt":1677668400,"temp":13.8,"feels_like":12.93,"pressure":1018,"humidity":65,"dew_point":7.11,"uvi":0,"clouds":87,"visibility":10000,"wind_speed":7.08,"wind_deg":203,"wind_gust":12.58,"weather":[{"id":804,"main":"Clouds","description":"厚い雲","icon":"04n"}],"pop":0},{"dt":1677672000,"temp":13.67,"feels_like":12.87,"pressure":1017,"humidity":68,"dew_point":7.61,"uvi":0,"clouds":89,"visibility":10000,"wind_speed":7.04,"wind_deg":209,"wind_gust":12.21,"weather":[{"id":804,"main":"Clouds","description":"厚い雲","icon":"04n"}],"pop":0},{"dt":1677675600,"temp":13.58,"feels_like":12.85,"pressure":1017,"humidity":71,"dew_point":8.11,"uvi":0,"clouds":100,"visibility":10000,"wind_speed":6.84,"wind_deg":210,"wind_gust":12.54,"weather":[{"id":804,"main":"Clouds","description":"厚い雲","icon":"04n"}],"pop":0.04},{"dt":1677679200,"temp":13.74,"feels_like":12.95,"pressure":1017,"humidity":68,"dew_point":7.75,"uvi":0,"clouds":100,"visibility":10000,"wind_speed":7.66,"wind_deg":222,"wind_gust":12.27,"weather":[{"id":804,"main":"Clouds","description":"厚い雲","icon":"04n"}],"pop":0.19},{"dt":1677682800,"temp":13.08,"feels_like":12.14,"pressure":1016,"humidity":65,"dew_point":6.35,"uvi":0,"clouds":100,"visibility":10000,"wind_speed":4.9,"wind_deg":265,"wind_gust":8.39,"weather":[{"id":500,"main":"Rain","description":"小雨","icon":"10n"}],"pop":0.31,"rain":{"1h":0.13}},{"dt":1677686400,"temp":11.84,"feels_like":10.88,"pressure":1016,"humidity":69,"dew_point":6.16,"uvi":0,"clouds":99,"visibility":10000,"wind_speed":4.65,"wind_deg":273,"wind_gust":9.85,"weather":[{"id":804,"main":"Clouds","description":"厚い雲","icon":"04n"}],"pop":0.47},{"dt":1677690000,"temp":12.23,"feels_like":11.39,"pressure":1016,"humidity":72,"dew_point":7,"uvi":0,"clouds":100,"visibility":10000,"wind_speed":6.38,"wind_deg":261,"wind_gust":11.66,"weather":[{"id":500,"main":"Rain","description":"小雨","icon":"10n"}],"pop":0.64,"rain":{"1h":0.14}},{"dt":1677693600,"temp":11.88,"feels_like":11,"pressure":1015,"humidity":72,"dew_point":6.69,"uvi":0,"clouds":100,"visibility":10000,"wind_speed":6.01,"wind_deg":265,"wind_gust":10.7,"weather":[{"id":804,"main":"Clouds","description":"厚い雲","icon":"04n"}],"pop":0.64},{"dt":1677697200,"temp":11.33,"feels_like":10.56,"pressure":1015,"humidity":78,"dew_point":7.36,"uvi":0,"clouds":100,"visibility":10000,"wind_speed":4.49,"wind_deg":260,"wind_gust":9.04,"weather":[{"id":500,"main":"Rain","description":"小雨","icon":"10n"}],"pop":0.63,"rain":{"1h":0.13}},{"dt":1677700800,"temp":10.96,"feels_like":9.91,"pressure":1016,"humidity":69,"dew_point":5.2,"uvi":0,"clouds":80,"visibility":10000,"wind_speed":5.02,"wind_deg":278,"wind_gust":8.98,"weather":[{"id":500,"main":"Rain","description":"小雨","icon":"10n"}],"pop":0.68,"rain":{"1h":0.23}}],"daily":[{"dt":1677553200,"sunrise":1677533385,"sunset":1677574317,"moonrise":1677550380,"moonset":1677515340,"moon_phase":0.27,"temp":{"day":13.2,"min":2.33,"max":14.32,"night":10.49,"eve":12.76,"morn":2.33},"feels_like":{"day":11.91,"night":9.37,"eve":11.66,"morn":2.33},"pressure":1030,"humidity":51,"dew_point":2.99,"wind_speed":7.03,"wind_deg":235,"wind_gust":9.3,"weather":[{"id":800,"main":"Clear","description":"晴天","icon":"01d"}],"clouds":0,"pop":0,"uvi":5.05},{"dt":1677639600,"sunrise":1677619710,"sunset":1677660770,"moonrise":1677639600,"moonset":1677605220,"moon_phase":0.3,"temp":{"day":14.96,"min":8.3,"max":15.65,"night":13.74,"eve":14.81,"morn":8.4},"feels_like":{"day":13.66,"night":12.95,"eve":13.76,"morn":8.4},"pressure":1023,"humidity":44,"dew_point":2.42,"wind_speed":7.66,"wind_deg":222,"wind_gust":13.67,"weather":[{"id":801,"main":"Clouds","description":"薄い雲","icon":"02d"}],"clouds":14,"pop":0.19,"uvi":5.12},{"dt":1677726000,"sunrise":1677706034,"sunset":1677747223,"moonrise":1677729060,"moonset":1677694860,"moon_phase":0.34,"temp":{"day":8.96,"min":5.73,"max":13.08,"night":5.78,"eve":6.7,"morn":9.88},"feels_like":{"day":4.94,"night":2.77,"eve":2.87,"morn":7.74},"pressure":1022,"humidity":38,"dew_point":-4.6,"wind_speed":10.04,"wind_deg":330,"wind_gust":13.18,"weather":[{"id":500,"main":"Rain","description":"小雨","icon":"10d"}],"clouds":25,"pop":0.68,"rain":0.63,"uvi":3.98},{"dt":1677812400,"sunrise":1677792357,"sunset":1677833675,"moonrise":1677818880,"moonset":1677784080,"moon_phase":0.37,"temp":{"day":9.77,"min":4.24,"max":11.59,"night":9.22,"eve":9.95,"morn":4.24},"feels_like":{"day":8.63,"night":8.64,"eve":8.64,"morn":4.24},"pressure":1027,"humidity":34,"dew_point":-5.68,"wind_speed":2.9,"wind_deg":231,"wind_gust":6.16,"weather":[{"id":800,"main":"Clear","description":"晴天","icon":"01d"}],"clouds":0,"pop":0,"uvi":4.86},{"dt":1677898800,"sunrise":1677878680,"sunset":1677920127,"moonrise":1677908760,"moonset":1677872940,"moon_phase":0.4,"temp":{"day":12.52,"min":6.26,"max":14.35,"night":9.73,"eve":11.95,"morn":6.26},"feels_like":{"day":10.69,"night":7.68,"eve":10.17,"morn":6.26},"pressure":1027,"humidity":33,"dew_point":-3.34,"wind_speed":4.82,"wind_deg":349,"wind_gust":6.31,"weather":[{"id":804,"main":"Clouds","description":"厚い雲","icon":"04d"}],"clouds":100,"pop":0,"uvi":4.38},{"dt":1677985200,"sunrise":1677965001,"sunset":1678006578,"moonrise":1677998700,"moonset":1677961500,"moon_phase":0.43,"temp":{"day":13.86,"min":8.21,"max":14.87,"night":10.06,"eve":11.3,"morn":8.21},"feels_like":{"day":12.45,"night":8.95,"eve":10.18,"morn":6.67},"pressure":1025,"humidity":44,"dew_point":1.72,"wind_speed":5.84,"wind_deg":72,"wind_gust":8.35,"weather":[{"id":804,"main":"Clouds","description":"厚い雲","icon":"04d"}],"clouds":94,"pop":0.4,"uvi":5},{"dt":1678071600,"sunrise":1678051323,"sunset":1678093029,"moonrise":1678088640,"moonset":1678049700,"moon_phase":0.46,"temp":{"day":13.73,"min":8.26,"max":13.91,"night":9.31,"eve":11.7,"morn":8.26},"feels_like":{"day":12.33,"night":7.33,"eve":10.07,"morn":6.7},"pressure":1020,"humidity":45,"dew_point":1.69,"wind_speed":5.85,"wind_deg":351,"wind_gust":8.91,"weather":[{"id":500,"main":"Rain","description":"小雨","icon":"10d"}],"clouds":37,"pop":0.52,"rain":1.93,"uvi":5},{"dt":1678158000,"sunrise":1678137643,"sunset":1678179480,"moonrise":1678178520,"moonset":1678137780,"moon_phase":0.5,"temp":{"day":13.1,"min":7,"max":15.29,"night":13.21,"eve":14.1,"morn":7},"feels_like":{"day":11.75,"night":12.21,"eve":12.82,"morn":7},"pressure":1021,"humidity":49,"dew_point":2.24,"wind_speed":4.58,"wind_deg":229,"wind_gust":6.7,"weather":[{"id":802,"main":"Clouds","description":"雲","icon":"03d"}],"clouds":48,"pop":0.11,"uvi":5}]}