{"lat":34.7338,"lon":135.5014,"timezone":"Asia/Tokyo","timezone_offset":32400,"current":{"dt":1696627374,"sunrise":1696625786,"sunset":1696667725,"temp":15.93,"feels_like":15.07,"pressure":1018,"humidity":57,"dew_point":7.43,"uvi":0,"clouds":98,"visibility":10000,"wind_speed":2.06,"wind_deg":310,"weather":[{"id":804,"main":"Clouds","description":"厚い雲","icon":"04d"}]},"hourly":[{"dt":1696626000,"temp":15.93,"feels_like":15.07,"pressure":1018,"humidity":57,"dew_point":7.43,"uvi":0,"clouds":98,"visibility":10000,"wind_speed":2.49,"wind_deg":333,"wind_gust":7.04,"weather":[{"id":804,"main":"Clouds","description":"厚い雲","icon":"04d"}],"pop":0},{"dt":1696629600,"temp":16.37,"feels_like":15.5,"pressure":1018,"humidity":55,"dew_point":7.32,"uvi":0.21,"clouds":98,"visibility":10000,"wind_speed":2.53,"wind_deg":338,"wind_gust":7.02,"weather":[{"id":804,"main":"Clouds","description":"厚い雲","icon":"04d"}],"pop":0},{"dt":1696633200,"temp":17.29,"feels_like":16.46,"pressure":1019,"humidity":53,"dew_point":7.63,"uvi":0.95,"clouds":95,"visibility":10000,"wind_speed":3.84,"wind_deg":349,"wind_gust":8.96,"weather":[{"id":804,"main":"Clouds","description":"厚い雲","icon":"04d"}],"pop":0},{"dt":1696636800,"temp":18.81,"feels_like":18,"pressure":1019,"humidity":48,"dew_point":7.58,"uvi":2.29,"clouds":94,"visibility":10000,"wind_speed":4.98,"wind_deg":358,"wind_gust":8.29,"weather":[{"id":804,"main":"Clouds","description":"厚い雲","icon":"04d"}],"pop":0},{"dt":1696640400,"temp":20.58,"feels_like":19.76,"pressure":1020,"humidity":41,"dew_point":6.88,"uvi":3.98,"clouds":100,"visibility":10000,"wind_speed":6.18,"wind_deg":357,"wind_gust":7.97,"weather":[{"id":804,"main":"Clouds","description":"厚い雲","icon":"04d"}],"pop":0},{"dt":1696644000,"temp":22.39,"feels_like":21.6,"pressure":1020,"humidity":35,"dew_point":6.19,"uvi":5.35,"clouds":100,"visibility":10000,"wind_speed":6.54,"wind_deg":1,"wind_gust":8.17,"weather":[{"id":804,"main":"Clouds","description":"厚い雲","icon":"04d"}],"pop":0},{"dt":1696647600,"temp":22.99,"feels_like":22.21,"pressure":1019,"humidity":33,"dew_point":5.77,"uvi":5.85,"clouds":93,"visibility":10000,"wind_speed":6.45,"wind_deg":360,"wind_gust":7.97,"weather":[{"id":804,"main":"Clouds","description":"厚い雲","icon":"04d"}],"pop":0},{"dt":1696651200,"temp":23.36,"feels_like":22.59,"pressure":1019,"humidity":32,"dew_point":5.68,"uvi":5.44,"clouds":90,"visibility":10000,"wind_speed":6.98,"wind_deg":358,"wind_gust":8.26,"weather":[{"id":804,"main":"Clouds","description":"厚い雲","icon":"04d"}],"pop":0},{"dt":1696654800,"temp":23.11,"feels_like":22.36,"pressure":1019,"humidity":34,"dew_point":6.42,"uvi":3.99,"clouds":85,"visibility":10000,"wind_speed":7.5,"wind_deg":9,"wind_gust":8.48,"weather":[{"id":804,"main":"Clouds","description":"厚い雲","icon":"04d"}],"pop":0},{"dt":1696658400,"temp":22.58,"feels_like":21.78,"pressure":1019,"humidity":34,"dew_point":5.89,"uvi":2.26,"clouds":73,"visibility":10000,"wind_speed":7.13,"wind_deg":9,"wind_gust":8.16,"weather":[{"id":803,"main":"Clouds","description":"曇りがち","icon":"04d"}],"pop":0},{"dt":1696662000,"temp":21.55,"feels_like":20.78,"pressure":1020,"humidity":39,"dew_point":6.64,"uvi":0.9,"clouds":50,"visibility":10000,"wind_speed":7.26,"wind_deg":8,"wind_gust":8.54,"weather":[{"id":802,"main":"Clouds","description":"雲","icon":"03d"}],"pop":0},{"dt":1696665600,"temp":20.34,"feels_like":19.63,"pressure":1020,"humidity":46,"dew_point":8.07,"uvi":0.19,"clouds":36,"visibility":10000,"wind_speed":6.39,"wind_deg":4,"wind_gust":8.64,"weather":[{"id":802,"main":"Clouds","description":"雲","icon":"03d"}],"pop":0},{"dt":1696669200,"temp":19.7,"feels_like":18.98,"pressure":1021,"humidity":48,"dew_point":8.11,"uvi":0,"clouds":58,"visibility":10000,"wind_speed":5.33,"wind_deg":2,"wind_gust":8.55,"weather":[{"id":803,"main":"Clouds","description":"曇りがち","icon":"04n"}],"pop":0},{"dt":1696672800,"temp":19.43,"feels_like":18.68,"pressure":1021,"humidity":48,"dew_point":7.97,"uvi":0,"clouds":68,"visibility":10000,"wind_speed":4.36,"wind_deg":3,"wind_gust":8.14,"weather":[{"id":803,"main":"Clouds","description":"曇りがち","icon":"04n"}],"pop":0},{"dt":1696676400,"temp":19.31,"feels_like":18.55,"pressure":1022,"humidity":48,"dew_point":7.79,"uvi":0,"clouds":75,"visibility":10000,"wind_speed":3.97,"wind_deg":2,"wind_gust":8.49,"weather":[{"id":803,"main":"Clouds","description":"曇りがち","icon":"04n"}],"pop":0},{"dt":1696680000,"temp":19.18,"feels_like":18.41,"pressure":1022,"humidity":48,"dew_point":7.86,"uvi":0,"clouds":78,"visibility":10000,"wind_speed":3.15,"wind_deg":359,"wind_gust":7.9,"weather":[{"id":803,"main":"Clouds","description":"曇りがち","icon":"04n"}],"pop":0},{"dt":1696683600,"temp":19.1,"feels_like":18.35,"pressure":1022,"humidity":49,"dew_point":7.87,"uvi":0,"clouds":97,"visibility":10000,"wind_speed":2.54,"wind_deg":4,"wind_gust":7.18,"weather":[{"id":804,"main":"Clouds","description":"厚い雲","icon":"04n"}],"pop":0},{"dt":1696687200,"temp":18.8,"feels_like":18.04,"pressure":1022,"humidity":50,"dew_point":7.97,"uvi":0,"clouds":96,"visibility":10000,"wind_speed":2.01,"wind_deg":3,"wind_gust":6.4,"weather":[{"id":804,"main":"Clouds","description":"厚い雲","icon":"04n"}],"pop":0},{"dt":1696690800,"temp":18.54,"feels_like":17.78,"pressure":1022,"humidity":51,"dew_point":8.07,"uvi":0,"clouds":92,"visibility":10000,"wind_speed":1.73,"wind_deg":6,"wind_gust":4.88,"weather":[{"id":804,"main":"Clouds","description":"厚い雲","icon":"04n"}],"pop":0},{"dt":1696694400,"temp":18.12,"feels_like":17.4,"pressure":1022,"humidity":54,"dew_point":8.35,"uvi":0,"clouds":93,"visibility":10000,"wind_speed":2,"wind_deg":17,"wind_gust":5.07,"weather":[{"id":804,"main":"Clouds","description":"厚い雲","icon":"04n"}],"pop":0},{"dt":1696698000,"temp":17.64,"feels_like":16.95,"pressure":1022,"humidity":57,"dew_point":8.73,"uvi":0,"clouds":92,"visibility":10000,"wind_speed":1.42,"wind_deg":31,"wind_gust":2.79,"weather":[{"id":804,"main":"Clouds","description":"厚い雲","icon":"04n"}],"pop":0},{"dt":1696701600,"temp":17.43,"feels_like":16.74,"pressure":1022,"humidity":58,"dew_point":8.85,"uvi":0,"clouds":93,"visibility":10000,"wind_speed":1.41,"wind_deg":53,"wind_gust":2.47,"weather":[{"id":804,"main":"Clouds","description":"厚い雲","icon":"04n"}],"pop":0},{"dt":1696705200,"temp":17.04,"feels_like":16.37,"pressure":1021,"humidity":60,"dew_point":9.03,"uvi":0,"clouds":100,"visibility":10000,"wind_speed":1.6,"wind_deg":51,"wind_gust":2.97,"weather":[{"id":804,"main":"Clouds","description":"厚い雲","icon":"04n"}],"pop":0},{"dt":1696708800,"temp":16.75,"feels_like":16.1,"pressure":1022,"humidity":62,"dew_point":9.23,"uvi":0,"clouds":100,"visibility":10000,"wind_speed":2.08,"wind_deg":37,"wind_gust":3.59,"weather":[{"id":804,"main":"Clouds","description":"厚い雲","icon":"04n"}],"pop":0},{"dt":1696712400,"temp":16.63,"feels_like":15.99,"pressure":1022,"humidity":63,"dew_point":9.24,"uvi":0,"clouds":100,"visibility":10000,"wind_speed":2.02,"wind_deg":40,"wind_gust":3.53,"weather":[{"id":804,"main":"Clouds","description":"厚い雲","icon":"04d"}],"pop":0},{"dt":1696716000,"temp":16.94,"feels_like":16.26,"pressure":1022,"humidity":60,"dew_point":9.13,"uvi":0.16,"clouds":100,"visibility":10000,"wind_speed":2.03,"wind_deg":54,"wind_gust":3.19,"weather":[{"id":804,"main":"Clouds","description":"厚い雲","icon":"04d"}],"pop":0},{"dt":1696719600,"temp":17.95,"feels_like":17.24,"pressure":1023,"humidity":55,"dew_point":8.58,"uvi":0.72,"clouds":100,"visibility":10000,"wind_speed":2.43,"wind_deg":35,"wind_gust":3.35,"weather":[{"id":804,"main":"Clouds","description":"厚い雲","icon":"04d"}],"pop":0},{"dt":1696723200,"temp":18.69,"feels_like":17.95,"pressure":1022,"humidity":51,"dew_point":7.99,"uvi":1.76,"clouds":100,"visibility":10000,"wind_speed":3.1,"wind_deg":52,"wind_gust":3.86,"weather":[{"id":804,"main":"Clouds","description":"厚い雲","icon":"04d"}],"pop":0},{"dt":1696726800,"temp":19.18,"feels_like":18.38,"pressure":1022,"humidity":47,"dew_point":7.48,"uvi":1.97,"clouds":100,"visibility":10000,"wind_speed":3.03,"wind_deg":58,"wind_gust":3.69,"weather":[{"id":804,"main":"Clouds","description":"厚い雲","icon":"04d"}],"pop":0.04},{"dt":1696730400,"temp":19.82,"feels_like":19.03,"pressure":1022,"humidity":45,"dew_point":7.16,"uvi":2.64,"clouds":100,"visibility":10000,"wind_speed":2.7,"wind_deg":44,"wind_gust":3.06,"weather":[{"id":804,"main":"Clouds","description":"厚い雲","icon":"04d"}],"pop":0.13},{"dt":1696734000,"temp":19.41,"feels_like":18.69,"pressure":1023,"humidity":49,"dew_point":8.08,"uvi":2.89,"clouds":100,"visibility":10000,"wind_speed":3.51,"wind_deg":98,"wind_gust":3.4,"weather":[{"id":500,"main":"Rain","description":"小雨","icon":"10d"}],"pop":0.37,"rain":{"1h":0.16}},{"dt":1696737600,"temp":16.65,"feels_like":16.22,"pressure":1022,"humidity":71,"dew_point":11.17,"uvi":0.62,"clouds":100,"visibility":10000,"wind_speed":3.17,"wind_deg":100,"wind_gust":3.5,"weather":[{"id":500,"main":"Rain","description":"小雨","icon":"10d"}],"pop":0.53,"rain":{"1h":0.69}},{"dt":1696741200,"temp":15.89,"feels_like":15.62,"pressure":1022,"humidity":80,"dew_point":12.18,"uvi":0.45,"clouds":100,"visibility":7743,"wind_speed":2.39,"wind_deg":99,"wind_gust":2.74,"weather":[{"id":501,"main":"Rain","description":"適度な雨","icon":"10d"}],"pop":0.77,"rain":{"1h":1.35}},{"dt":1696744800,"temp":15.67,"feels_like":15.49,"pressure":1022,"humidity":84,"dew_point":12.64,"uvi":0.26,"clouds":100,"visibility":7150,"wind_speed":1.9,"wind_deg":35,"wind_gust":2.62,"weather":[{"id":501,"main":"Rain","description":"適度な雨","icon":"10d"}],"pop":0.89,"rain":{"1h":1.92}},{"dt":1696748400,"temp":15.69,"feels_like":15.51,"pressure":1023,"humidity":84,"dew_point":12.75,"uvi":0.07,"clouds":100,"visibility":9073,"wind_speed":2.88,"wind_deg":25,"wind_gust":3.82,"weather":[{"id":501,"main":"Rain","description":"適度な雨","icon":"10d"}],"pop":1,"rain":{"1h":2.11}},{"dt":1696752000,"temp":15.55,"feels_like":15.33,"pressure":1022,"humidity":83,"dew_point":12.23,"uvi":0.01,"clouds":100,"visibility":10000,"wind_speed":3.32,"wind_deg":24,"wind_gust":4.83,"weather":[{"id":501,"main":"Rain","description":"適度な雨","icon":"10d"}],"pop":1,"rain":{"1h":1.28}},{"dt":1696755600,"temp":15.56,"feels_like":15.34,"pressure":1022,"humidity":83,"dew_point":12.43,"uvi":0,"clouds":100,"visibility":10000,"wind_speed":4.06,"wind_deg":15,"wind_gust":6.15,"weather":[{"id":500,"main":"Rain","description":"小雨","icon":"10n"}],"pop":1,"rain":{"1h":0.51}},{"dt":1696759200,"temp":16.11,"feels_like":16.02,"pressure":1022,"humidity":86,"dew_point":13.48,"uvi":0,"clouds":100,"visibility":10000,"wind_speed":3.86,"wind_deg":42,"wind_gust":8.37,"weather":[{"id":500,"main":"Rain","description":"小雨","icon":"10n"}],"pop":1,"rain":{"1h":0.12}},{"dt":1696762800,"temp":16.19,"feels_like":16.08,"pressure":1023,"humidity":85,"dew_point":13.47,"uvi":0,"clouds":100,"visibility":10000,"wind_speed":3.42,"wind_deg":30,"wind_gust":7.46,"weather":[{"id":500,"main":"Rain","description":"小雨","icon":"10n"}],"pop":1,"rain":{"1h":0.12}},{"dt":1696766400,"temp":16.06,"feels_like":15.97,"pressure":1023,"humidity":86,"dew_point":13.42,"uvi":0,"clouds":100,"visibility":10000,"wind_speed":4.17,"wind_deg":20,"wind_gust":6.68,"weather":[{"id":500,"main":"Rain","description":"小雨","icon":"10n"}],"pop":1,"rain":{"1h":0.42}},{"dt":1696770000,"temp":15.8,"feels_like":15.73,"pressure":1023,"humidity":88,"dew_point":13.47,"uvi":0,"clouds":100,"visibility":10000,"wind_speed":4.66,"wind_deg":28,"wind_gust":7.87,"weather":[{"id":500,"main":"Rain","description":"小雨","icon":"10n"}],"pop":0.59,"rain":{"1h":0.7}},{"dt":1696773600,"temp":15.84,"feels_like":15.75,"pressure":1022,"humidity":87,"dew_point":13.47,"uvi":0,"clouds":100,"visibility":10000,"wind_speed":4.73,"wind_deg":33,"wind_gust":8.69,"weather":[{"id":804,"main":"Clouds","description":"厚い雲","icon":"04n"}],"pop":0.59},{"dt":1696777200,"temp":16.01,"feels_like":15.91,"pressure":1022,"humidity":86,"dew_point":13.37,"uvi":0,"clouds":100,"visibility":10000,"wind_speed":4.18,"wind_deg":23,"wind_gust":8.3,"weather":[{"id":804,"main":"Clouds","description":"厚い雲","icon":"04n"}],"pop":0.55},{"dt":1696780800,"temp":16.19,"feels_like":16.06,"pressure":1021,"humidity":84,"dew_point":13.3,"uvi":0,"clouds":100,"visibility":10000,"wind_speed":4.52,"wind_deg":29,"wind_gust":8.26,"weather":[{"id":804,"main":"Clouds","description":"厚い雲","icon":"04n"}],"pop":0.51},{"dt":1696784400,"temp":16.2,"feels_like":16.1,"pressure":1021,"humidity":85,"dew_point":13.41,"uvi":0,"clouds":100,"visibility":10000,"wind_speed":4.39,"wind_deg":39,"wind_gust":8.94,"weather":[{"id":804,"main":"Clouds","description":"厚い雲","icon":"04n"}],"pop":0.51},{"dt":1696788000,"temp":16.38,"feels_like":16.29,"pressure":1020,"humidity":85,"dew_point":13.56,"uvi":0,"clouds":100,"visibility":10000,"wind_speed":4.1,"wind_deg":40,"wind_gust":8.89,"weather":[{"id":804,"main":"Clouds","description":"厚い雲","icon":"04n"}],"pop":0.43},{"dt":1696791600,"temp":16.6,"feels_like":16.51,"pressure":1020,"humidity":84,"dew_point":13.76,"uvi":0,"clouds":100,"visibility":10000,"wind_speed":3.99,"wind_deg":49,"wind_gust":8.85,"weather":[{"id":804,"main":"Clouds","description":"厚い雲","icon":"04n"}],"pop":0.24},{"dt":1696795200,"temp":16.77,"feels_like":16.7,"pressure":1020,"humidity":84,"dew_point":13.75,"uvi":0,"clouds":100,"visibility":10000,"wind_speed":4.31,"wind_deg":40,"wind_gust":8.92,"weather":[{"id":804,"main":"Clouds","description":"厚い雲","icon":"04n"}],"pop":0.39}],"daily":[{"dt":1696644000,"sunrise":1696625786,"sunset":1696667725,"moonrise":1696688940,"moonset":1696654260,"moon_phase":0.77,"temp":{"day":22.39,"min":15.93,"max":23.36,"night":18.8,"eve":20.34,"morn":16.24},"feels_like":{"day":21.6,"night":18.04,"eve":19.63,"morn":15.38},"pressure":1020,"humidity":35,"dew_point":6.19,"wind_speed":7.5,"wind_deg":9,"wind_gust":8.96,"weather":[{"id":804,"main":"Clouds","description":"厚い雲","icon":"04d"}],"clouds":100,"pop":0,"uvi":5.85},{"dt":1696730400,"sunrise":1696712232,"sunset":1696754043,"moonrise":0,"moonset":1696743060,"moon_phase":0.8,"temp":{"day":19.82,"min":15.55,"max":19.82,"night":15.84,"eve":15.55,"morn":16.75},"feels_like":{"day":19.03,"night":15.75,"eve":15.33,"morn":16.1},"pressure":1022,"humidity":45,"dew_point":7.16,"wind_speed":4.73,"wind_deg":33,"wind_gust":8.69,"weather":[{"id":501,"main":"Rain","description":"適度な雨","icon":"10d"}],"clouds":100,"pop":1,"rain":9.38,"uvi":2.89},{"dt":1696816800,"sunrise":1696798679,"sunset":1696840362,"moonrise":1696778940,"moonset":1696831560,"moon_phase":0.83,"temp":{"day":20.01,"min":16.01,"max":22.1,"night":20,"eve":21.24,"morn":16.77},"feels_like":{"day":19.92,"night":20.04,"eve":21.22,"morn":16.7},"pressure":1019,"humidity":71,"dew_point":14.28,"wind_speed":4.52,"wind_deg":29,"wind_gust":8.94,"weather":[{"id":500,"main":"Rain","description":"小雨","icon":"10d"}],"clouds":100,"pop":0.55,"rain":0.17,"uvi":3.86},{"dt":1696903200,"sunrise":1696885126,"sunset":1696926681,"moonrise":1696868880,"moonset":1696919700,"moon_phase":0.86,"temp":{"day":24.78,"min":18.33,"max":24.78,"night":19.89,"eve":20.32,"morn":18.33},"feels_like":{"day":24.49,"night":19.53,"eve":20.05,"morn":18.39},"pressure":1015,"humidity":45,"dew_point":11.72,"wind_speed":7.78,"wind_deg":338,"wind_gust":9.93,"weather":[{"id":500,"main":"Rain","description":"小雨","icon":"10d"}],"clouds":17,"pop":0.51,"rain":0.61,"uvi":5.58},{"dt":1696989600,"sunrise":1696971573,"sunset":1697013001,"moonrise":1696958760,"moonset":1697007660,"moon_phase":0.89,"temp":{"day":22.59,"min":17.47,"max":22.59,"night":18.76,"eve":19.4,"morn":17.47},"feels_like":{"day":21.9,"night":18.1,"eve":18.7,"morn":17},"pressure":1021,"humidity":38,"dew_point":7.27,"wind_speed":6.7,"wind_deg":5,"wind_gust":10.04,"weather":[{"id":804,"main":"Clouds","description":"厚い雲","icon":"04d"}],"clouds":100,"pop":0,"uvi":4.83},{"dt":1697076000,"sunrise":1697058021,"sunset":1697099321,"moonrise":1697048580,"moonset":1697095500,"moon_phase":0.92,"temp":{"day":23.15,"min":15.38,"max":24.7,"night":18.81,"eve":20.61,"morn":15.38},"feels_like":{"day":22.59,"night":18.31,"eve":20.08,"morn":14.72},"pressure":1021,"humidity":41,"dew_point":9.04,"wind_speed":5.4,"wind_deg":346,"wind_gust":7.33,"weather":[{"id":800,"main":"Clear","description":"晴天","icon":"01d"}],"clouds":0,"pop":0.05,"uvi":5},{"dt":1697162400,"sunrise":1697144469,"sunset":1697185642,"moonrise":1697138400,"moonset":1697183280,"moon_phase":0.95,"temp":{"day":23.39,"min":15.99,"max":23.76,"night":19.06,"eve":21.1,"morn":15.99},"feels_like":{"day":22.88,"night":18.61,"eve":20.62,"morn":15.52},"pressure":1017,"humidity":42,"dew_point":9.46,"wind_speed":3.66,"wind_deg":355,"wind_gust":4.89,"weather":[{"id":802,"main":"Clouds","description":"雲","icon":"03d"}],"clouds":39,"pop":0.04,"uvi":5},{"dt":1697248800,"sunrise":1697230918,"sunset":1697271964,"moonrise":1697228220,"moonset":1697271120,"moon_phase":0.98,"temp":{"day":22.51,"min":17.21,"max":22.51,"night":19.93,"eve":20.31,"morn":17.21},"feels_like":{"day":22.12,"night":19.7,"eve":20.07,"morn":16.81},"pressure":1013,"humidity":50,"dew_point":11.33,"wind_speed":4.21,"wind_deg":254,"wind_gust":4.37,"weather":[{"id":500,"main":"Rain","description":"小雨","icon":"10d"}],"clouds":100,"pop":0.91,"rain":0.45,"uvi":5}]}